Workbook

Sheet README
A1: Tiered Cake Company — Finance (Phase 1e)
A3: Owners: Swetha (S) · Shreya (Sh)
A4: Tabs: Money In · Bank vs UPI Float · UPI Reconciliation · Compliance · Money Out · Vendor Ledger · P&L (monthly) · Cash Runway · Capex Register · Founder Draws
A5: Generated: 2026-05-24
A8: 1. IMPORT INTO GOOGLE SHEETS
A9: - sheets.google.com → File → Import → Upload → select this .xlsx → 'Replace spreadsheet'
A10: - Rename the spreadsheet to '03_Finance' (or similar)
A12: 2. DELETE THE EXAMPLE ROWS (highlighted yellow) once you've eyeballed them
A13: - Money In tab: sample rows match CRM sample orders for reconciler demo
A15: 3. SET OPENING BALANCES
A16: - Bank vs UPI Float tab: set Opening balance (₹) and Opening date for each account
A17: - These are typed once and never edited again
... A30: Header rows are dark; freeze panes set on row 1 of every tab.

Sheet Money In
A1: Entry ID | B1: Date | C1: Time | D1: Channel | E1: Account credited | F1: Amount (₹) | G1: UPI reference (UTR) | H1: Payer VPA | I1: Counter-party name | J1: Matched Order ID | K1: Notes | L1: Logged at
A2: =IF(B2="","","MIN-"&TEXT(ROW()-1,"0000")) | B2: 46040 | C2: 0.48055556 | D2: UPI-GPay | E2: UPI float | F2: 1400 | G2: 422118203341 | H2: arjun.mehta@oksbi | I2: Arjun Mehta | J2: ORD-0001 | K2: Deposit for Veer's bday cake | L2: =IF(B2="","",NOW())
A3: =IF(B3="","","MIN-"&TEXT(ROW()-1,"0000")) | B3: 46044 | C3: 0.38541667 | D3: UPI-GPay | E3: UPI float | F3: 1400 | G3: 422199876541 | H3: arjun.mehta@oksbi | I3: Arjun Mehta | J3: ORD-0001 | K3: Balance on delivery | L3: =IF(B3="","",NOW())
A4: =IF(B4="","","MIN-"&TEXT(ROW()-1,"0000")) | B4: 46067 | C4: 0.59861111 | D4: UPI-PhonePe | E4: UPI float | F4: 500 | G4: 431229104852 | H4: priya.r@okhdfcbank | I4: Priya Reddy | J4: ORD-0002 | K4: Valentine cupcakes deposit | L4: =IF(B4="","",NOW())
A5: =IF(B5="","","MIN-"&TEXT(ROW()-1,"0000")) | B5: 46069 | C5: 0.40277778 | D5: UPI-PhonePe | E5: UPI float | F5: 1000 | G5: 431288773322 | H5: priya.r@okhdfcbank | I5: Priya Reddy | J5: ORD-0002 | K5: Balance on pickup | L5: =IF(B5="","",NOW())
A6: =IF(B6="","","MIN-"&TEXT(ROW()-1,"0000")) | B6: 45993 | C6: 0.67013889 | D6: Bank Transfer | E6: Bank | F6: 2000 | I6: Cordant Software India Pvt Ltd | J6: ORD-0003 | K6: NEFT for office anniversary cake — invoice ref CRD-1130 | L6: =IF(B6="","",NOW())
A7: =IF(B7="","","MIN-"&TEXT(ROW()-1,"0000")) | B7: 46086 | C7: 0.84583333 | D7: UPI-GPay | E7: UPI float | F7: 2000 | G7: 445533781290 | H7: anjali.a@okaxis | I7: Anjali Agarwal | J7: ORD-0004 | K7: Myra's bday cake deposit | L7: =IF(B7="","",NOW())
A8: =IF(B8="","","MIN-"&TEXT(ROW()-1,"0000")) | B8: 46090 | C8: 0.42013889 | D8: UPI-GPay | E8: UPI float | F8: 2500 | G8: 445599883344 | H8: anjali.a@okaxis | I8: Anjali Agarwal | J8: ORD-0004 | K8: Balance on delivery | L8: =IF(B8="","",NOW())
A9: =IF(B9="","","MIN-"&TEXT(ROW()-1,"0000")) | B9: 46020 | C9: 0.64444444 | D9: UPI-GPay | E9: UPI float | F9: 1800 | G9: 449988102345 | H9: rohan.k@okicici | I9: Rohan Kapoor | J9: ORD-0005 | K9: Anniversary cake — full payment on pickup | L9: =IF(B9="","",NOW())
A10: =IF(B10="","","MIN-"&TEXT(ROW()-1,"0000")) | B10: 46156 | C10: 0.49305556 | D10: UPI-PhonePe | E10: UPI float | F10: 1500 | G10: 520011445566 | H10: sandeep.g@okhdfcbank | I10: Sandeep Goyal | J10: ORD-0006 | K10: Diwali trial deposit | L10: =IF(B10="","",NOW())
A11: =IF(B11="","","MIN-"&TEXT(ROW()-1,"0000")) | B11: 46160 | C11: 0.4375 | D11: UPI-PhonePe | E11: UPI float | F11: 1500 | G11: 520055667788 | H11: sandeep.g@okhdfcbank | I11: Sandeep Goyal | J11: ORD-0006 | K11: Balance on delivery | L11: =IF(B11="","",NOW())
A12: =IF(B12="","","MIN-"&TEXT(ROW()-1,"0000")) | B12: 46160 | C12: 0.92361111 | D12: UPI-GPay | E12: UPI float | F12: 1100 | G12: 521122876543 | H12: sneha.i@oksbi | I12: Sneha Iyer | J12: ORD-0007 | K12: Bday cake deposit | L12: =IF(B12="","",NOW())
A13: =IF(B13="","","MIN-"&TEXT(ROW()-1,"0000")) | B13: 46164 | C13: 0.38888889 | D13: UPI-GPay | E13: UPI float | F13: 1100 | G13: 521166998877 | H13: sneha.i@oksbi | I13: Sneha Iyer | J13: ORD-0007 | K13: Balance on delivery | L13: =IF(B13="","",NOW())
A14: =IF(B14="","","MIN-"&TEXT(ROW()-1,"0000")) | B14: 46164 | C14: 0.58888889 | D14: UPI-PhonePe | E14: UPI float | F14: 1500 | G14: 522233998877 | H14: vikram.b@okhdfcbank | I14: Vikram Bhatia | J14: ORD-0008 | K14: Anniversary cake deposit; balance on 27 May | L14: =IF(B14="","",NOW())
A15: =IF(B15="","","MIN-"&TEXT(ROW()-1,"0000")) | B15: 46165 | C15: 0.82291667 | D15: UPI-PhonePe | E15: UPI float | F15: 1500 | G15: 522288554433 | H15: priya.r@okhdfcbank | I15: Priya Reddy | J15: ORD-0009 | K15: Aarav's bday cake deposit | L15: =IF(B15="","",NOW())
A16: =IF(B16="","","MIN-"&TEXT(ROW()-1,"0000")) | B16: 46164 | C16: 0.85416667 | D16: UPI-GPay | E16: UPI float | F16: 700 | G16: 523344112266 | H16: aditi.s@oksbi | I16: Aditi Saxena | J16: ORD-0010 | K16: Bomboloni box deposit | L16: =IF(B16="","",NOW())
A17: =IF(B17="","","MIN-"&TEXT(ROW()-1,"0000")) | B17: 46162 | C17: 0.45833333 | D17: UPI-GPay | E17: UPI float | F17: 50 | G17: 519988774422 | H17: unknown.payer@oksbi | I17: Karthik (mistype?) | K17: ₹50 — possibly a tip or mistaken send; investigate | L17: =IF(B17="","",NOW())
A18: =IF(B18="","","MIN-"&TEXT(ROW()-1,"0000")) | B18: 46163 | C18: 0.71875 | D18: Cash | E18: Cash drawer | F18: 300 | I18: Walk-in customer (neighbour) | K18: Sold 6 leftover brownies; not a CRM order | L18: =IF(B18="","",NOW())
A19: =IF(B19="","","MIN-"&TEXT(ROW()-1,"0000")) | L19: =IF(B19="","",NOW())
A20: =IF(B20="","","MIN-"&TEXT(ROW()-1,"0000")) | L20: =IF(B20="","",NOW())
A21: =IF(B21="","","MIN-"&TEXT(ROW()-1,"0000")) | L21: =IF(B21="","",NOW())
A22: =IF(B22="","","MIN-"&TEXT(ROW()-1,"0000")) | L22: =IF(B22="","",NOW())
A23: =IF(B23="","","MIN-"&TEXT(ROW()-1,"0000")) | L23: =IF(B23="","",NOW())
A24: =IF(B24="","","MIN-"&TEXT(ROW()-1,"0000")) | L24: =IF(B24="","",NOW())
A25: =IF(B25="","","MIN-"&TEXT(ROW()-1,"0000")) | L25: =IF(B25="","",NOW())
A26: =IF(B26="","","MIN-"&TEXT(ROW()-1,"0000")) | L26: =IF(B26="","",NOW())
A27: =IF(B27="","","MIN-"&TEXT(ROW()-1,"0000")) | L27: =IF(B27="","",NOW())
A28: =IF(B28="","","MIN-"&TEXT(ROW()-1,"0000")) | L28: =IF(B28="","",NOW())
A29: =IF(B29="","","MIN-"&TEXT(ROW()-1,"0000")) | L29: =IF(B29="","",NOW())
A30: =IF(B30="","","MIN-"&TEXT(ROW()-1,"0000")) | L30: =IF(B30="","",NOW())
... A501: =IF(B501="","","MIN-"&TEXT(ROW()-1,"0000")) | L501: =IF(B501="","",NOW())

Sheet Bank vs UPI Float
A1: Account | B1: Opening balance (₹) | C1: Opening date | D1: Inflows since opening (₹) | E1: Outflows since opening (₹) | F1: Current balance (₹) | G1: Last reconciled (date) | H1: Variance vs actual (₹) | I1: Notes
A2: Bank — HDFC Current | B2: 25000 | C2: 45962 | D2: =IFERROR(SUMIFS('Money In'!F:F,'Money In'!E:E,IF(LEFT(A2,4)="Bank","Bank",IF(LEFT(A2,3)="UPI","UPI float","Cash drawer")),'Money In'!B:B,">="&C2),0) | E2: =IFERROR(SUMIFS('Money Out'!F:F,'Money Out'!E:E,IF(LEFT(A2,4)="Bank","Bank",IF(LEFT(A2,3)="UPI","UPI float","Cash drawer")),'Money Out'!B:B,">="&C2),0) | F2: =IF(A2="","",B2+D2-E2) | G2: 46162 | H2: 0 | I2: Personal current account; bakery uses it provisionally
A3: UPI — GPay (Swetha phone) | B3: 5000 | C3: 45962 | D3: =IFERROR(SUMIFS('Money In'!F:F,'Money In'!E:E,IF(LEFT(A3,4)="Bank","Bank",IF(LEFT(A3,3)="UPI","UPI float","Cash drawer")),'Money In'!B:B,">="&C3),0) | E3: =IFERROR(SUMIFS('Money Out'!F:F,'Money Out'!E:E,IF(LEFT(A3,4)="Bank","Bank",IF(LEFT(A3,3)="UPI","UPI float","Cash drawer")),'Money Out'!B:B,">="&C3),0) | F3: =IF(A3="","",B3+D3-E3) | G3: 46165 | H3: 0 | I3: Primary inflow channel
A4: UPI — PhonePe (Shreya phone) | B4: 1000 | C4: 45962 | D4: =IFERROR(SUMIFS('Money In'!F:F,'Money In'!E:E,IF(LEFT(A4,4)="Bank","Bank",IF(LEFT(A4,3)="UPI","UPI float","Cash drawer")),'Money In'!B:B,">="&C4),0) | E4: =IFERROR(SUMIFS('Money Out'!F:F,'Money Out'!E:E,IF(LEFT(A4,4)="Bank","Bank",IF(LEFT(A4,3)="UPI","UPI float","Cash drawer")),'Money Out'!B:B,">="&C4),0) | F4: =IF(A4="","",B4+D4-E4) | G4: 46165 | H4: 0 | I4: Secondary; some customers default here
A5: Cash drawer | B5: 500 | C5: 45962 | D5: =IFERROR(SUMIFS('Money In'!F:F,'Money In'!E:E,IF(LEFT(A5,4)="Bank","Bank",IF(LEFT(A5,3)="UPI","UPI float","Cash drawer")),'Money In'!B:B,">="&C5),0) | E5: =IFERROR(SUMIFS('Money Out'!F:F,'Money Out'!E:E,IF(LEFT(A5,4)="Bank","Bank",IF(LEFT(A5,3)="UPI","UPI float","Cash drawer")),'Money Out'!B:B,">="&C5),0) | F5: =IF(A5="","",B5+D5-E5) | G5: 46162 | H5: 0 | I5: Float for change-making
D6: =IFERROR(SUMIFS('Money In'!F:F,'Money In'!E:E,IF(LEFT(A6,4)="Bank","Bank",IF(LEFT(A6,3)="UPI","UPI float","Cash drawer")),'Money In'!B:B,">="&C6),0) | E6: =IFERROR(SUMIFS('Money Out'!F:F,'Money Out'!E:E,IF(LEFT(A6,4)="Bank","Bank",IF(LEFT(A6,3)="UPI","UPI float","Cash drawer")),'Money Out'!B:B,">="&C6),0) | F6: =IF(A6="","",B6+D6-E6)
D7: =IFERROR(SUMIFS('Money In'!F:F,'Money In'!E:E,IF(LEFT(A7,4)="Bank","Bank",IF(LEFT(A7,3)="UPI","UPI float","Cash drawer")),'Money In'!B:B,">="&C7),0) | E7: =IFERROR(SUMIFS('Money Out'!F:F,'Money Out'!E:E,IF(LEFT(A7,4)="Bank","Bank",IF(LEFT(A7,3)="UPI","UPI float","Cash drawer")),'Money Out'!B:B,">="&C7),0) | F7: =IF(A7="","",B7+D7-E7)
D8: =IFERROR(SUMIFS('Money In'!F:F,'Money In'!E:E,IF(LEFT(A8,4)="Bank","Bank",IF(LEFT(A8,3)="UPI","UPI float","Cash drawer")),'Money In'!B:B,">="&C8),0) | E8: =IFERROR(SUMIFS('Money Out'!F:F,'Money Out'!E:E,IF(LEFT(A8,4)="Bank","Bank",IF(LEFT(A8,3)="UPI","UPI float","Cash drawer")),'Money Out'!B:B,">="&C8),0) | F8: =IF(A8="","",B8+D8-E8)
D9: =IFERROR(SUMIFS('Money In'!F:F,'Money In'!E:E,IF(LEFT(A9,4)="Bank","Bank",IF(LEFT(A9,3)="UPI","UPI float","Cash drawer")),'Money In'!B:B,">="&C9),0) | E9: =IFERROR(SUMIFS('Money Out'!F:F,'Money Out'!E:E,IF(LEFT(A9,4)="Bank","Bank",IF(LEFT(A9,3)="UPI","UPI float","Cash drawer")),'Money Out'!B:B,">="&C9),0) | F9: =IF(A9="","",B9+D9-E9)
D10: =IFERROR(SUMIFS('Money In'!F:F,'Money In'!E:E,IF(LEFT(A10,4)="Bank","Bank",IF(LEFT(A10,3)="UPI","UPI float","Cash drawer")),'Money In'!B:B,">="&C10),0) | E10: =IFERROR(SUMIFS('Money Out'!F:F,'Money Out'!E:E,IF(LEFT(A10,4)="Bank","Bank",IF(LEFT(A10,3)="UPI","UPI float","Cash drawer")),'Money Out'!B:B,">="&C10),0) | F10: =IF(A10="","",B10+D10-E10)
D11: =IFERROR(SUMIFS('Money In'!F:F,'Money In'!E:E,IF(LEFT(A11,4)="Bank","Bank",IF(LEFT(A11,3)="UPI","UPI float","Cash drawer")),'Money In'!B:B,">="&C11),0) | E11: =IFERROR(SUMIFS('Money Out'!F:F,'Money Out'!E:E,IF(LEFT(A11,4)="Bank","Bank",IF(LEFT(A11,3)="UPI","UPI float","Cash drawer")),'Money Out'!B:B,">="&C11),0) | F11: =IF(A11="","",B11+D11-E11)

Sheet UPI Reconciliation
A1: UPI Reconciliation — last run: (pending first run of upi_reconciler.gs)
A3: SECTION A — Inflows without a matched Order
A5: Entry ID | B5: Date | C5: Amount (₹) | D5: UTR | E5: Payer VPA | F5: Counter-party | G5: Channel | H5: Action
A6: (populated by upi_reconciler.gs — run daily 09:00 IST)
A25: SECTION B — Orders claiming UPI payment but no matching inflow
A27: Order ID | B27: Customer | C27: Delivery date | D27: Final (₹) | E27: Declared paid (₹) | F27: Orders.UTR | G27: Payment mode | H27: Action
A28: (populated by upi_reconciler.gs)
A45: SECTION C — Summary
A46: Inflows without a match: | B46: (pending)
A47: Orders without a match: | B47: (pending)
A48: ₹ unmatched (inflow side): | B48: (pending)
A49: ₹ unmatched (order side): | B49: (pending)
A50: Last run: | B50: (never)

Sheet Compliance
A1: License type | B1: License number | C1: Issuing authority | D1: Issued on | E1: Valid until | F1: Days to expiry | G1: Status | H1: Last renewed | I1: Notes
A2: FSSAI Cottage Food | B2: 21024010000001 | C2: Telangana FSSAI | D2: 46068 | E2: 46432 | F2: =IFERROR(E2-TODAY(),"") | G2: =IF(F2="","",IF(F2<0,"EXPIRED",IF(F2<=7,"Renew NOW",IF(F2<=30,"Renew this month",IF(F2<=90,"Renew this quarter","Current"))))) | H2: 46068 | I2: Annual renewal — calendar reminder 30 days ahead. Cottage food licence covers ≤₹12L annual turnover.
A3: Trade Licence | B3: TL-2026-CFB-44521 | C3: GHMC (Greater Hyderabad) | D3: 46082 | E3: 47177 | F3: =IFERROR(E3-TODAY(),"") | G3: =IF(F3="","",IF(F3<0,"EXPIRED",IF(F3<=7,"Renew NOW",IF(F3<=30,"Renew this month",IF(F3<=90,"Renew this quarter","Current"))))) | H3: 46082 | I3: 3-year cycle. Applies because operating from residential premises with commercial intent.
A4: GST Registration | C4: GSTN | F4: =IFERROR(E4-TODAY(),"") | G4: =IF(F4="","",IF(F4<0,"EXPIRED",IF(F4<=7,"Renew NOW",IF(F4<=30,"Renew this month",IF(F4<=90,"Renew this quarter","Current"))))) | I4: Voluntary registration deferred. Activate when annual turnover crosses ₹40L (goods threshold in Telangana). Tracked here for forward compat.
F5: =IFERROR(E5-TODAY(),"") | G5: =IF(F5="","",IF(F5<0,"EXPIRED",IF(F5<=7,"Renew NOW",IF(F5<=30,"Renew this month",IF(F5<=90,"Renew this quarter","Current")))))
F6: =IFERROR(E6-TODAY(),"") | G6: =IF(F6="","",IF(F6<0,"EXPIRED",IF(F6<=7,"Renew NOW",IF(F6<=30,"Renew this month",IF(F6<=90,"Renew this quarter","Current")))))
F7: =IFERROR(E7-TODAY(),"") | G7: =IF(F7="","",IF(F7<0,"EXPIRED",IF(F7<=7,"Renew NOW",IF(F7<=30,"Renew this month",IF(F7<=90,"Renew this quarter","Current")))))
F8: =IFERROR(E8-TODAY(),"") | G8: =IF(F8="","",IF(F8<0,"EXPIRED",IF(F8<=7,"Renew NOW",IF(F8<=30,"Renew this month",IF(F8<=90,"Renew this quarter","Current")))))
F9: =IFERROR(E9-TODAY(),"") | G9: =IF(F9="","",IF(F9<0,"EXPIRED",IF(F9<=7,"Renew NOW",IF(F9<=30,"Renew this month",IF(F9<=90,"Renew this quarter","Current")))))
F10: =IFERROR(E10-TODAY(),"") | G10: =IF(F10="","",IF(F10<0,"EXPIRED",IF(F10<=7,"Renew NOW",IF(F10<=30,"Renew this month",IF(F10<=90,"Renew this quarter","Current")))))
F11: =IFERROR(E11-TODAY(),"") | G11: =IF(F11="","",IF(F11<0,"EXPIRED",IF(F11<=7,"Renew NOW",IF(F11<=30,"Renew this month",IF(F11<=90,"Renew this quarter","Current")))))
F12: =IFERROR(E12-TODAY(),"") | G12: =IF(F12="","",IF(F12<0,"EXPIRED",IF(F12<=7,"Renew NOW",IF(F12<=30,"Renew this month",IF(F12<=90,"Renew this quarter","Current")))))
F13: =IFERROR(E13-TODAY(),"") | G13: =IF(F13="","",IF(F13<0,"EXPIRED",IF(F13<=7,"Renew NOW",IF(F13<=30,"Renew this month",IF(F13<=90,"Renew this quarter","Current")))))
F14: =IFERROR(E14-TODAY(),"") | G14: =IF(F14="","",IF(F14<0,"EXPIRED",IF(F14<=7,"Renew NOW",IF(F14<=30,"Renew this month",IF(F14<=90,"Renew this quarter","Current")))))
F15: =IFERROR(E15-TODAY(),"") | G15: =IF(F15="","",IF(F15<0,"EXPIRED",IF(F15<=7,"Renew NOW",IF(F15<=30,"Renew this month",IF(F15<=90,"Renew this quarter","Current")))))
F16: =IFERROR(E16-TODAY(),"") | G16: =IF(F16="","",IF(F16<0,"EXPIRED",IF(F16<=7,"Renew NOW",IF(F16<=30,"Renew this month",IF(F16<=90,"Renew this quarter","Current")))))
... F51: =IFERROR(E51-TODAY(),"") | G51: =IF(F51="","",IF(F51<0,"EXPIRED",IF(F51<=7,"Renew NOW",IF(F51<=30,"Renew this month",IF(F51<=90,"Renew this quarter","Current")))))

Sheet Money Out
A1: Entry ID | B1: Date | C1: Time | D1: Channel | E1: Account debited | F1: Amount (₹) | G1: Category | H1: UPI reference (UTR) | I1: Payee VPA / Account | J1: Payee name | K1: Linked PO ID | L1: Notes | M1: Logged at
A2: =IF(B2="","","MOUT-"&TEXT(ROW()-1,"0000")) | B2: 46146 | C2: 0.46875 | D2: UPI-PhonePe | E2: UPI float | F2: 2840 | G2: Ingredients | H2: 510044112233 | I2: metrocc@hdfcbank | J2: Metro Cash & Carry | K2: PO-0001 | L2: Weekly flour + sugar + butter restock | M2: =IF(B2="","",NOW())
A3: =IF(B3="","","MOUT-"&TEXT(ROW()-1,"0000")) | B3: 46149 | C3: 0.77083333 | D3: UPI-GPay | E3: UPI float | F3: 1450 | G3: Ingredients | H3: 510077665544 | I3: vijetha@oksbi | J3: Vijetha Supermarket | L3: Milk, cream, eggs — top-up | M3: =IF(B3="","",NOW())
A4: =IF(B4="","","MOUT-"&TEXT(ROW()-1,"0000")) | B4: 46153 | C4: 0.41666667 | D4: UPI-GPay | E4: UPI float | F4: 920 | G4: Ingredients | H4: 510099887766 | I4: heritage@okhdfc | J4: Heritage Dairy | L4: Fresh paneer + cream for week's cakes | M4: =IF(B4="","",NOW())
A5: =IF(B5="","","MOUT-"&TEXT(ROW()-1,"0000")) | B5: 46156 | C5: 0.65625 | D5: UPI-PhonePe | E5: UPI float | F5: 3200 | G5: Ingredients | H5: 511122334455 | I5: callebaut@okicici | J5: Callebaut Distributor — Hyd | K5: PO-0002 | L5: Couverture chocolate 5kg block | M5: =IF(B5="","",NOW())
A6: =IF(B6="","","MOUT-"&TEXT(ROW()-1,"0000")) | B6: 46151 | C6: 0.55555556 | D6: Bank Transfer | E6: Bank | F6: 4500 | G6: Packaging | I6: wholesale-box-supplier | J6: Wholesale Box Supplier — Madhapur | K6: PO-0003 | L6: 100 × 1kg cake boxes + 50 × cupcake clamshells | M6: =IF(B6="","",NOW())
A7: =IF(B7="","","MOUT-"&TEXT(ROW()-1,"0000")) | B7: 46144 | C7: 0.375 | D7: UPI-GPay | E7: Bank | F7: 1850 | G7: Utilities | I7: ghmc@billdesk | J7: GHMC (electricity) | L7: April electricity bill | M7: =IF(B7="","",NOW())
A8: =IF(B8="","","MOUT-"&TEXT(ROW()-1,"0000")) | B8: 46148 | C8: 0.35416667 | D8: Cash | E8: Cash drawer | F8: 1180 | G8: Utilities | J8: Bharat Gas (cylinder delivery boy) | L8: 1 × 14.2kg LPG refill | M8: =IF(B8="","",NOW())
A9: =IF(B9="","","MOUT-"&TEXT(ROW()-1,"0000")) | B9: 46164 | C9: 0.39236111 | D9: UPI-GPay | E9: UPI float | F9: 95 | G9: Delivery (Porter/Dunzo) | H9: 521144556677 | I9: porter@axis | J9: Porter (Vikram's anniversary cake delivery) | L9: Same-day; 6.4 km | M9: =IF(B9="","",NOW())
A10: =IF(B10="","","MOUT-"&TEXT(ROW()-1,"0000")) | B10: 46160 | C10: 0.44791667 | D10: UPI-GPay | E10: UPI float | F10: 70 | G10: Delivery (Porter/Dunzo) | H10: 521133445566 | I10: porter@axis | J10: Porter (Sneha's bday cake delivery) | L10: Eterna pickup → Eterna drop, 1.2 km | M10: =IF(B10="","",NOW())
A11: =IF(B11="","","MOUT-"&TEXT(ROW()-1,"0000")) | B11: 46154 | C11: 0.58333333 | D11: Bank Transfer | E11: Bank | F11: 38000 | G11: Equipment (capex) | I11: kitchenaid-india | J11: KitchenAid India (Amazon) | K11: PO-0004 | L11: 5KSM150 stand mixer — Phase 1 capex | M11: =IF(B11="","",NOW())
A12: =IF(B12="","","MOUT-"&TEXT(ROW()-1,"0000")) | B12: 46157 | C12: 0.83333333 | D12: UPI-GPay | E12: Bank | F12: 15000 | G12: Founder Draw | I12: swetha@oksbi | J12: Swetha (founder draw) | L12: Salary equivalent — May | M12: =IF(B12="","",NOW())
A13: =IF(B13="","","MOUT-"&TEXT(ROW()-1,"0000")) | B13: 46157 | C13: 0.83680556 | D13: UPI-GPay | E13: Bank | F13: 15000 | G13: Founder Draw | I13: shreya@okhdfc | J13: Shreya (founder draw) | L13: Salary equivalent — May | M13: =IF(B13="","",NOW())
A14: =IF(B14="","","MOUT-"&TEXT(ROW()-1,"0000")) | M14: =IF(B14="","",NOW())
A15: =IF(B15="","","MOUT-"&TEXT(ROW()-1,"0000")) | M15: =IF(B15="","",NOW())
A16: =IF(B16="","","MOUT-"&TEXT(ROW()-1,"0000")) | M16: =IF(B16="","",NOW())
A17: =IF(B17="","","MOUT-"&TEXT(ROW()-1,"0000")) | M17: =IF(B17="","",NOW())
A18: =IF(B18="","","MOUT-"&TEXT(ROW()-1,"0000")) | M18: =IF(B18="","",NOW())
A19: =IF(B19="","","MOUT-"&TEXT(ROW()-1,"0000")) | M19: =IF(B19="","",NOW())
A20: =IF(B20="","","MOUT-"&TEXT(ROW()-1,"0000")) | M20: =IF(B20="","",NOW())
A21: =IF(B21="","","MOUT-"&TEXT(ROW()-1,"0000")) | M21: =IF(B21="","",NOW())
A22: =IF(B22="","","MOUT-"&TEXT(ROW()-1,"0000")) | M22: =IF(B22="","",NOW())
A23: =IF(B23="","","MOUT-"&TEXT(ROW()-1,"0000")) | M23: =IF(B23="","",NOW())
A24: =IF(B24="","","MOUT-"&TEXT(ROW()-1,"0000")) | M24: =IF(B24="","",NOW())
A25: =IF(B25="","","MOUT-"&TEXT(ROW()-1,"0000")) | M25: =IF(B25="","",NOW())
... A501: =IF(B501="","","MOUT-"&TEXT(ROW()-1,"0000")) | M501: =IF(B501="","",NOW())

Sheet Vendor Ledger
A1: Vendor name | B1: Category | C1: Preferred channel | D1: VPA / Account | E1: Total paid to date (₹) | F1: Last payment date | G1: Payment count | H1: Notes
A2: Metro Cash & Carry | B2: Ingredient supplier | C2: UPI-PhonePe | D2: metrocc@hdfcbank | E2: =IFERROR(SUMIFS('Money Out'!F:F,'Money Out'!J:J,A2),0) | F2: =IFERROR(IF(MAXIFS('Money Out'!B:B,'Money Out'!J:J,A2)=0,"",MAXIFS('Money Out'!B:B,'Money Out'!J:J,A2)),"") | G2: =IF(A2="","",COUNTIF('Money Out'!J:J,A2)) | H2: HoReCa account; bulk buys; visit weekly
A3: Vijetha Supermarket | B3: Ingredient supplier | C3: UPI-GPay | D3: vijetha@oksbi | E3: =IFERROR(SUMIFS('Money Out'!F:F,'Money Out'!J:J,A3),0) | F3: =IFERROR(IF(MAXIFS('Money Out'!B:B,'Money Out'!J:J,A3)=0,"",MAXIFS('Money Out'!B:B,'Money Out'!J:J,A3)),"") | G3: =IF(A3="","",COUNTIF('Money Out'!J:J,A3)) | H3: Top-up shop within walking distance
A4: Heritage Dairy | B4: Ingredient supplier | C4: UPI-GPay | D4: heritage@okhdfc | E4: =IFERROR(SUMIFS('Money Out'!F:F,'Money Out'!J:J,A4),0) | F4: =IFERROR(IF(MAXIFS('Money Out'!B:B,'Money Out'!J:J,A4)=0,"",MAXIFS('Money Out'!B:B,'Money Out'!J:J,A4)),"") | G4: =IF(A4="","",COUNTIF('Money Out'!J:J,A4)) | H4: Fresh dairy 2x/week
A5: Callebaut Distributor — Hyd | B5: Ingredient supplier | C5: UPI-PhonePe | D5: callebaut@okicici | E5: =IFERROR(SUMIFS('Money Out'!F:F,'Money Out'!J:J,A5),0) | F5: =IFERROR(IF(MAXIFS('Money Out'!B:B,'Money Out'!J:J,A5)=0,"",MAXIFS('Money Out'!B:B,'Money Out'!J:J,A5)),"") | G5: =IF(A5="","",COUNTIF('Money Out'!J:J,A5)) | H5: Couverture chocolate; 5kg blocks; lead time 2 days
A6: Wholesale Box Supplier — Madhapur | B6: Packaging | C6: Bank Transfer | D6: 9876543210@upi | E6: =IFERROR(SUMIFS('Money Out'!F:F,'Money Out'!J:J,A6),0) | F6: =IFERROR(IF(MAXIFS('Money Out'!B:B,'Money Out'!J:J,A6)=0,"",MAXIFS('Money Out'!B:B,'Money Out'!J:J,A6)),"") | G6: =IF(A6="","",COUNTIF('Money Out'!J:J,A6)) | H6: Cake boxes, cupcake clamshells, ribbons; MOQ 50
A7: GHMC (electricity) | B7: Utility | C7: UPI-GPay | D7: ghmc@billdesk | E7: =IFERROR(SUMIFS('Money Out'!F:F,'Money Out'!J:J,A7),0) | F7: =IFERROR(IF(MAXIFS('Money Out'!B:B,'Money Out'!J:J,A7)=0,"",MAXIFS('Money Out'!B:B,'Money Out'!J:J,A7)),"") | G7: =IF(A7="","",COUNTIF('Money Out'!J:J,A7)) | H7: Auto-debit option pending
A8: Bharat Gas | B8: Utility | C8: Cash | E8: =IFERROR(SUMIFS('Money Out'!F:F,'Money Out'!J:J,A8),0) | F8: =IFERROR(IF(MAXIFS('Money Out'!B:B,'Money Out'!J:J,A8)=0,"",MAXIFS('Money Out'!B:B,'Money Out'!J:J,A8)),"") | G8: =IF(A8="","",COUNTIF('Money Out'!J:J,A8)) | H8: Cylinder delivery; cash to delivery boy
A9: Porter | B9: Delivery partner | C9: UPI-GPay | D9: porter@axis | E9: =IFERROR(SUMIFS('Money Out'!F:F,'Money Out'!J:J,A9),0) | F9: =IFERROR(IF(MAXIFS('Money Out'!B:B,'Money Out'!J:J,A9)=0,"",MAXIFS('Money Out'!B:B,'Money Out'!J:J,A9)),"") | G9: =IF(A9="","",COUNTIF('Money Out'!J:J,A9)) | H9: Same-day local deliveries; pay per ride
A10: KitchenAid India (Amazon) | B10: Capex supplier | C10: Bank Transfer | E10: =IFERROR(SUMIFS('Money Out'!F:F,'Money Out'!J:J,A10),0) | F10: =IFERROR(IF(MAXIFS('Money Out'!B:B,'Money Out'!J:J,A10)=0,"",MAXIFS('Money Out'!B:B,'Money Out'!J:J,A10)),"") | G10: =IF(A10="","",COUNTIF('Money Out'!J:J,A10)) | H10: One-off; stand mixer; warranty 2 years
E11: =IFERROR(SUMIFS('Money Out'!F:F,'Money Out'!J:J,A11),0) | F11: =IFERROR(IF(MAXIFS('Money Out'!B:B,'Money Out'!J:J,A11)=0,"",MAXIFS('Money Out'!B:B,'Money Out'!J:J,A11)),"") | G11: =IF(A11="","",COUNTIF('Money Out'!J:J,A11))
E12: =IFERROR(SUMIFS('Money Out'!F:F,'Money Out'!J:J,A12),0) | F12: =IFERROR(IF(MAXIFS('Money Out'!B:B,'Money Out'!J:J,A12)=0,"",MAXIFS('Money Out'!B:B,'Money Out'!J:J,A12)),"") | G12: =IF(A12="","",COUNTIF('Money Out'!J:J,A12))
E13: =IFERROR(SUMIFS('Money Out'!F:F,'Money Out'!J:J,A13),0) | F13: =IFERROR(IF(MAXIFS('Money Out'!B:B,'Money Out'!J:J,A13)=0,"",MAXIFS('Money Out'!B:B,'Money Out'!J:J,A13)),"") | G13: =IF(A13="","",COUNTIF('Money Out'!J:J,A13))
E14: =IFERROR(SUMIFS('Money Out'!F:F,'Money Out'!J:J,A14),0) | F14: =IFERROR(IF(MAXIFS('Money Out'!B:B,'Money Out'!J:J,A14)=0,"",MAXIFS('Money Out'!B:B,'Money Out'!J:J,A14)),"") | G14: =IF(A14="","",COUNTIF('Money Out'!J:J,A14))
E15: =IFERROR(SUMIFS('Money Out'!F:F,'Money Out'!J:J,A15),0) | F15: =IFERROR(IF(MAXIFS('Money Out'!B:B,'Money Out'!J:J,A15)=0,"",MAXIFS('Money Out'!B:B,'Money Out'!J:J,A15)),"") | G15: =IF(A15="","",COUNTIF('Money Out'!J:J,A15))
E16: =IFERROR(SUMIFS('Money Out'!F:F,'Money Out'!J:J,A16),0) | F16: =IFERROR(IF(MAXIFS('Money Out'!B:B,'Money Out'!J:J,A16)=0,"",MAXIFS('Money Out'!B:B,'Money Out'!J:J,A16)),"") | G16: =IF(A16="","",COUNTIF('Money Out'!J:J,A16))
E17: =IFERROR(SUMIFS('Money Out'!F:F,'Money Out'!J:J,A17),0) | F17: =IFERROR(IF(MAXIFS('Money Out'!B:B,'Money Out'!J:J,A17)=0,"",MAXIFS('Money Out'!B:B,'Money Out'!J:J,A17)),"") | G17: =IF(A17="","",COUNTIF('Money Out'!J:J,A17))
E18: =IFERROR(SUMIFS('Money Out'!F:F,'Money Out'!J:J,A18),0) | F18: =IFERROR(IF(MAXIFS('Money Out'!B:B,'Money Out'!J:J,A18)=0,"",MAXIFS('Money Out'!B:B,'Money Out'!J:J,A18)),"") | G18: =IF(A18="","",COUNTIF('Money Out'!J:J,A18))
E19: =IFERROR(SUMIFS('Money Out'!F:F,'Money Out'!J:J,A19),0) | F19: =IFERROR(IF(MAXIFS('Money Out'!B:B,'Money Out'!J:J,A19)=0,"",MAXIFS('Money Out'!B:B,'Money Out'!J:J,A19)),"") | G19: =IF(A19="","",COUNTIF('Money Out'!J:J,A19))
E20: =IFERROR(SUMIFS('Money Out'!F:F,'Money Out'!J:J,A20),0) | F20: =IFERROR(IF(MAXIFS('Money Out'!B:B,'Money Out'!J:J,A20)=0,"",MAXIFS('Money Out'!B:B,'Money Out'!J:J,A20)),"") | G20: =IF(A20="","",COUNTIF('Money Out'!J:J,A20))
E21: =IFERROR(SUMIFS('Money Out'!F:F,'Money Out'!J:J,A21),0) | F21: =IFERROR(IF(MAXIFS('Money Out'!B:B,'Money Out'!J:J,A21)=0,"",MAXIFS('Money Out'!B:B,'Money Out'!J:J,A21)),"") | G21: =IF(A21="","",COUNTIF('Money Out'!J:J,A21))
E22: =IFERROR(SUMIFS('Money Out'!F:F,'Money Out'!J:J,A22),0) | F22: =IFERROR(IF(MAXIFS('Money Out'!B:B,'Money Out'!J:J,A22)=0,"",MAXIFS('Money Out'!B:B,'Money Out'!J:J,A22)),"") | G22: =IF(A22="","",COUNTIF('Money Out'!J:J,A22))
... E101: =IFERROR(SUMIFS('Money Out'!F:F,'Money Out'!J:J,A101),0) | F101: =IFERROR(IF(MAXIFS('Money Out'!B:B,'Money Out'!J:J,A101)=0,"",MAXIFS('Money Out'!B:B,'Money Out'!J:J,A101)),"") | G101: =IF(A101="","",COUNTIF('Money Out'!J:J,A101))

Sheet P&L (monthly)
A1: Line item | B1: 2026-05 | C1: 2026-06 | D1: 2026-07 | E1: 2026-08 | F1: 2026-09 | G1: 2026-10 | H1: 2026-11 | I1: 2026-12 | J1: 2027-01 | K1: 2027-02 | L1: 2027-03 | M1: 2027-04
A2: REVENUE
A3: Gross revenue (orders) | B3: =SUMIFS('Money In'!F:F,'Money In'!J:J,"<>",'Money In'!B:B,">="&DATE(2026,5,1),'Money In'!B:B,"<="&DATE(2026,6,1)-1) | C3: =SUMIFS('Money In'!F:F,'Money In'!J:J,"<>",'Money In'!B:B,">="&DATE(2026,6,1),'Money In'!B:B,"<="&DATE(2026,7,1)-1) | D3: =SUMIFS('Money In'!F:F,'Money In'!J:J,"<>",'Money In'!B:B,">="&DATE(2026,7,1),'Money In'!B:B,"<="&DATE(2026,8,1)-1) | E3: =SUMIFS('Money In'!F:F,'Money In'!J:J,"<>",'Money In'!B:B,">="&DATE(2026,8,1),'Money In'!B:B,"<="&DATE(2026,9,1)-1) | F3: =SUMIFS('Money In'!F:F,'Money In'!J:J,"<>",'Money In'!B:B,">="&DATE(2026,9,1),'Money In'!B:B,"<="&DATE(2026,10,1)-1) | G3: =SUMIFS('Money In'!F:F,'Money In'!J:J,"<>",'Money In'!B:B,">="&DATE(2026,10,1),'Money In'!B:B,"<="&DATE(2026,11,1)-1) | H3: =SUMIFS('Money In'!F:F,'Money In'!J:J,"<>",'Money In'!B:B,">="&DATE(2026,11,1),'Money In'!B:B,"<="&DATE(2026,12,1)-1) | I3: =SUMIFS('Money In'!F:F,'Money In'!J:J,"<>",'Money In'!B:B,">="&DATE(2026,12,1),'Money In'!B:B,"<="&DATE(2027,1,1)-1) | J3: =SUMIFS('Money In'!F:F,'Money In'!J:J,"<>",'Money In'!B:B,">="&DATE(2027,1,1),'Money In'!B:B,"<="&DATE(2027,2,1)-1) | K3: =SUMIFS('Money In'!F:F,'Money In'!J:J,"<>",'Money In'!B:B,">="&DATE(2027,2,1),'Money In'!B:B,"<="&DATE(2027,3,1)-1) | L3: =SUMIFS('Money In'!F:F,'Money In'!J:J,"<>",'Money In'!B:B,">="&DATE(2027,3,1),'Money In'!B:B,"<="&DATE(2027,4,1)-1) | M3: =SUMIFS('Money In'!F:F,'Money In'!J:J,"<>",'Money In'!B:B,">="&DATE(2027,4,1),'Money In'!B:B,"<="&DATE(2027,5,1)-1)
A4: Other inflows (unmatched / refunds) | B4: =SUMIFS('Money In'!F:F,'Money In'!J:J,"",'Money In'!B:B,">="&DATE(2026,5,1),'Money In'!B:B,"<="&DATE(2026,6,1)-1) | C4: =SUMIFS('Money In'!F:F,'Money In'!J:J,"",'Money In'!B:B,">="&DATE(2026,6,1),'Money In'!B:B,"<="&DATE(2026,7,1)-1) | D4: =SUMIFS('Money In'!F:F,'Money In'!J:J,"",'Money In'!B:B,">="&DATE(2026,7,1),'Money In'!B:B,"<="&DATE(2026,8,1)-1) | E4: =SUMIFS('Money In'!F:F,'Money In'!J:J,"",'Money In'!B:B,">="&DATE(2026,8,1),'Money In'!B:B,"<="&DATE(2026,9,1)-1) | F4: =SUMIFS('Money In'!F:F,'Money In'!J:J,"",'Money In'!B:B,">="&DATE(2026,9,1),'Money In'!B:B,"<="&DATE(2026,10,1)-1) | G4: =SUMIFS('Money In'!F:F,'Money In'!J:J,"",'Money In'!B:B,">="&DATE(2026,10,1),'Money In'!B:B,"<="&DATE(2026,11,1)-1) | H4: =SUMIFS('Money In'!F:F,'Money In'!J:J,"",'Money In'!B:B,">="&DATE(2026,11,1),'Money In'!B:B,"<="&DATE(2026,12,1)-1) | I4: =SUMIFS('Money In'!F:F,'Money In'!J:J,"",'Money In'!B:B,">="&DATE(2026,12,1),'Money In'!B:B,"<="&DATE(2027,1,1)-1) | J4: =SUMIFS('Money In'!F:F,'Money In'!J:J,"",'Money In'!B:B,">="&DATE(2027,1,1),'Money In'!B:B,"<="&DATE(2027,2,1)-1) | K4: =SUMIFS('Money In'!F:F,'Money In'!J:J,"",'Money In'!B:B,">="&DATE(2027,2,1),'Money In'!B:B,"<="&DATE(2027,3,1)-1) | L4: =SUMIFS('Money In'!F:F,'Money In'!J:J,"",'Money In'!B:B,">="&DATE(2027,3,1),'Money In'!B:B,"<="&DATE(2027,4,1)-1) | M4: =SUMIFS('Money In'!F:F,'Money In'!J:J,"",'Money In'!B:B,">="&DATE(2027,4,1),'Money In'!B:B,"<="&DATE(2027,5,1)-1)
A5: Total revenue | B5: =B3+B4 | C5: =C3+C4 | D5: =D3+D4 | E5: =E3+E4 | F5: =F3+F4 | G5: =G3+G4 | H5: =H3+H4 | I5: =I3+I4 | ... M5: =M3+M4
A7: COGS (cost of goods sold)
A8: Ingredients | B8: =SUMIFS('Money Out'!F:F,'Money Out'!G:G,"Ingredients",'Money Out'!B:B,">="&DATE(2026,5,1),'Money Out'!B:B,"<="&DATE(2026,6,1)-1) | C8: =SUMIFS('Money Out'!F:F,'Money Out'!G:G,"Ingredients",'Money Out'!B:B,">="&DATE(2026,6,1),'Money Out'!B:B,"<="&DATE(2026,7,1)-1) | D8: =SUMIFS('Money Out'!F:F,'Money Out'!G:G,"Ingredients",'Money Out'!B:B,">="&DATE(2026,7,1),'Money Out'!B:B,"<="&DATE(2026,8,1)-1) | E8: =SUMIFS('Money Out'!F:F,'Money Out'!G:G,"Ingredients",'Money Out'!B:B,">="&DATE(2026,8,1),'Money Out'!B:B,"<="&DATE(2026,9,1)-1) | F8: =SUMIFS('Money Out'!F:F,'Money Out'!G:G,"Ingredients",'Money Out'!B:B,">="&DATE(2026,9,1),'Money Out'!B:B,"<="&DATE(2026,10,1)-1) | G8: =SUMIFS('Money Out'!F:F,'Money Out'!G:G,"Ingredients",'Money Out'!B:B,">="&DATE(2026,10,1),'Money Out'!B:B,"<="&DATE(2026,11,1)-1) | H8: =SUMIFS('Money Out'!F:F,'Money Out'!G:G,"Ingredients",'Money Out'!B:B,">="&DATE(2026,11,1),'Money Out'!B:B,"<="&DATE(2026,12,1)-1) | I8: =SUMIFS('Money Out'!F:F,'Money Out'!G:G,"Ingredients",'Money Out'!B:B,">="&DATE(2026,12,1),'Money Out'!B:B,"<="&DATE(2027,1,1)-1) | J8: =SUMIFS('Money Out'!F:F,'Money Out'!G:G,"Ingredients",'Money Out'!B:B,">="&DATE(2027,1,1),'Money Out'!B:B,"<="&DATE(2027,2,1)-1) | K8: =SUMIFS('Money Out'!F:F,'Money Out'!G:G,"Ingredients",'Money Out'!B:B,">="&DATE(2027,2,1),'Money Out'!B:B,"<="&DATE(2027,3,1)-1) | L8: =SUMIFS('Money Out'!F:F,'Money Out'!G:G,"Ingredients",'Money Out'!B:B,">="&DATE(2027,3,1),'Money Out'!B:B,"<="&DATE(2027,4,1)-1) | M8: =SUMIFS('Money Out'!F:F,'Money Out'!G:G,"Ingredients",'Money Out'!B:B,">="&DATE(2027,4,1),'Money Out'!B:B,"<="&DATE(2027,5,1)-1)
A9: Packaging | B9: =SUMIFS('Money Out'!F:F,'Money Out'!G:G,"Packaging",'Money Out'!B:B,">="&DATE(2026,5,1),'Money Out'!B:B,"<="&DATE(2026,6,1)-1) | C9: =SUMIFS('Money Out'!F:F,'Money Out'!G:G,"Packaging",'Money Out'!B:B,">="&DATE(2026,6,1),'Money Out'!B:B,"<="&DATE(2026,7,1)-1) | D9: =SUMIFS('Money Out'!F:F,'Money Out'!G:G,"Packaging",'Money Out'!B:B,">="&DATE(2026,7,1),'Money Out'!B:B,"<="&DATE(2026,8,1)-1) | E9: =SUMIFS('Money Out'!F:F,'Money Out'!G:G,"Packaging",'Money Out'!B:B,">="&DATE(2026,8,1),'Money Out'!B:B,"<="&DATE(2026,9,1)-1) | F9: =SUMIFS('Money Out'!F:F,'Money Out'!G:G,"Packaging",'Money Out'!B:B,">="&DATE(2026,9,1),'Money Out'!B:B,"<="&DATE(2026,10,1)-1) | G9: =SUMIFS('Money Out'!F:F,'Money Out'!G:G,"Packaging",'Money Out'!B:B,">="&DATE(2026,10,1),'Money Out'!B:B,"<="&DATE(2026,11,1)-1) | H9: =SUMIFS('Money Out'!F:F,'Money Out'!G:G,"Packaging",'Money Out'!B:B,">="&DATE(2026,11,1),'Money Out'!B:B,"<="&DATE(2026,12,1)-1) | I9: =SUMIFS('Money Out'!F:F,'Money Out'!G:G,"Packaging",'Money Out'!B:B,">="&DATE(2026,12,1),'Money Out'!B:B,"<="&DATE(2027,1,1)-1) | J9: =SUMIFS('Money Out'!F:F,'Money Out'!G:G,"Packaging",'Money Out'!B:B,">="&DATE(2027,1,1),'Money Out'!B:B,"<="&DATE(2027,2,1)-1) | K9: =SUMIFS('Money Out'!F:F,'Money Out'!G:G,"Packaging",'Money Out'!B:B,">="&DATE(2027,2,1),'Money Out'!B:B,"<="&DATE(2027,3,1)-1) | L9: =SUMIFS('Money Out'!F:F,'Money Out'!G:G,"Packaging",'Money Out'!B:B,">="&DATE(2027,3,1),'Money Out'!B:B,"<="&DATE(2027,4,1)-1) | M9: =SUMIFS('Money Out'!F:F,'Money Out'!G:G,"Packaging",'Money Out'!B:B,">="&DATE(2027,4,1),'Money Out'!B:B,"<="&DATE(2027,5,1)-1)
A10: Total COGS | B10: =B8+B9 | C10: =C8+C9 | D10: =D8+D9 | E10: =E8+E9 | F10: =F8+F9 | G10: =G8+G9 | H10: =H8+H9 | I10: =I8+I9 | ... M10: =M8+M9
A11: Gross profit | B11: =B5-B10 | C11: =C5-C10 | D11: =D5-D10 | E11: =E5-E10 | F11: =F5-F10 | G11: =G5-G10 | H11: =H5-H10 | I11: =I5-I10 | ... M11: =M5-M10
A12: Gross margin % | B12: =IFERROR(B11/B5,"") | C12: =IFERROR(C11/C5,"") | D12: =IFERROR(D11/D5,"") | E12: =IFERROR(E11/E5,"") | F12: =IFERROR(F11/F5,"") | G12: =IFERROR(G11/G5,"") | H12: =IFERROR(H11/H5,"") | I12: =IFERROR(I11/I5,"") | ... M12: =IFERROR(M11/M5,"")
A14: OPERATING EXPENSES
A15: Utilities | B15: =SUMIFS('Money Out'!F:F,'Money Out'!G:G,"Utilities",'Money Out'!B:B,">="&DATE(2026,5,1),'Money Out'!B:B,"<="&DATE(2026,6,1)-1) | C15: =SUMIFS('Money Out'!F:F,'Money Out'!G:G,"Utilities",'Money Out'!B:B,">="&DATE(2026,6,1),'Money Out'!B:B,"<="&DATE(2026,7,1)-1) | D15: =SUMIFS('Money Out'!F:F,'Money Out'!G:G,"Utilities",'Money Out'!B:B,">="&DATE(2026,7,1),'Money Out'!B:B,"<="&DATE(2026,8,1)-1) | E15: =SUMIFS('Money Out'!F:F,'Money Out'!G:G,"Utilities",'Money Out'!B:B,">="&DATE(2026,8,1),'Money Out'!B:B,"<="&DATE(2026,9,1)-1) | F15: =SUMIFS('Money Out'!F:F,'Money Out'!G:G,"Utilities",'Money Out'!B:B,">="&DATE(2026,9,1),'Money Out'!B:B,"<="&DATE(2026,10,1)-1) | G15: =SUMIFS('Money Out'!F:F,'Money Out'!G:G,"Utilities",'Money Out'!B:B,">="&DATE(2026,10,1),'Money Out'!B:B,"<="&DATE(2026,11,1)-1) | H15: =SUMIFS('Money Out'!F:F,'Money Out'!G:G,"Utilities",'Money Out'!B:B,">="&DATE(2026,11,1),'Money Out'!B:B,"<="&DATE(2026,12,1)-1) | I15: =SUMIFS('Money Out'!F:F,'Money Out'!G:G,"Utilities",'Money Out'!B:B,">="&DATE(2026,12,1),'Money Out'!B:B,"<="&DATE(2027,1,1)-1) | J15: =SUMIFS('Money Out'!F:F,'Money Out'!G:G,"Utilities",'Money Out'!B:B,">="&DATE(2027,1,1),'Money Out'!B:B,"<="&DATE(2027,2,1)-1) | K15: =SUMIFS('Money Out'!F:F,'Money Out'!G:G,"Utilities",'Money Out'!B:B,">="&DATE(2027,2,1),'Money Out'!B:B,"<="&DATE(2027,3,1)-1) | L15: =SUMIFS('Money Out'!F:F,'Money Out'!G:G,"Utilities",'Money Out'!B:B,">="&DATE(2027,3,1),'Money Out'!B:B,"<="&DATE(2027,4,1)-1) | M15: =SUMIFS('Money Out'!F:F,'Money Out'!G:G,"Utilities",'Money Out'!B:B,">="&DATE(2027,4,1),'Money Out'!B:B,"<="&DATE(2027,5,1)-1)
A16: Rent | B16: =SUMIFS('Money Out'!F:F,'Money Out'!G:G,"Rent",'Money Out'!B:B,">="&DATE(2026,5,1),'Money Out'!B:B,"<="&DATE(2026,6,1)-1) | C16: =SUMIFS('Money Out'!F:F,'Money Out'!G:G,"Rent",'Money Out'!B:B,">="&DATE(2026,6,1),'Money Out'!B:B,"<="&DATE(2026,7,1)-1) | D16: =SUMIFS('Money Out'!F:F,'Money Out'!G:G,"Rent",'Money Out'!B:B,">="&DATE(2026,7,1),'Money Out'!B:B,"<="&DATE(2026,8,1)-1) | E16: =SUMIFS('Money Out'!F:F,'Money Out'!G:G,"Rent",'Money Out'!B:B,">="&DATE(2026,8,1),'Money Out'!B:B,"<="&DATE(2026,9,1)-1) | F16: =SUMIFS('Money Out'!F:F,'Money Out'!G:G,"Rent",'Money Out'!B:B,">="&DATE(2026,9,1),'Money Out'!B:B,"<="&DATE(2026,10,1)-1) | G16: =SUMIFS('Money Out'!F:F,'Money Out'!G:G,"Rent",'Money Out'!B:B,">="&DATE(2026,10,1),'Money Out'!B:B,"<="&DATE(2026,11,1)-1) | H16: =SUMIFS('Money Out'!F:F,'Money Out'!G:G,"Rent",'Money Out'!B:B,">="&DATE(2026,11,1),'Money Out'!B:B,"<="&DATE(2026,12,1)-1) | I16: =SUMIFS('Money Out'!F:F,'Money Out'!G:G,"Rent",'Money Out'!B:B,">="&DATE(2026,12,1),'Money Out'!B:B,"<="&DATE(2027,1,1)-1) | J16: =SUMIFS('Money Out'!F:F,'Money Out'!G:G,"Rent",'Money Out'!B:B,">="&DATE(2027,1,1),'Money Out'!B:B,"<="&DATE(2027,2,1)-1) | K16: =SUMIFS('Money Out'!F:F,'Money Out'!G:G,"Rent",'Money Out'!B:B,">="&DATE(2027,2,1),'Money Out'!B:B,"<="&DATE(2027,3,1)-1) | L16: =SUMIFS('Money Out'!F:F,'Money Out'!G:G,"Rent",'Money Out'!B:B,">="&DATE(2027,3,1),'Money Out'!B:B,"<="&DATE(2027,4,1)-1) | M16: =SUMIFS('Money Out'!F:F,'Money Out'!G:G,"Rent",'Money Out'!B:B,">="&DATE(2027,4,1),'Money Out'!B:B,"<="&DATE(2027,5,1)-1)
A17: Maintenance | B17: =SUMIFS('Money Out'!F:F,'Money Out'!G:G,"Maintenance",'Money Out'!B:B,">="&DATE(2026,5,1),'Money Out'!B:B,"<="&DATE(2026,6,1)-1) | C17: =SUMIFS('Money Out'!F:F,'Money Out'!G:G,"Maintenance",'Money Out'!B:B,">="&DATE(2026,6,1),'Money Out'!B:B,"<="&DATE(2026,7,1)-1) | D17: =SUMIFS('Money Out'!F:F,'Money Out'!G:G,"Maintenance",'Money Out'!B:B,">="&DATE(2026,7,1),'Money Out'!B:B,"<="&DATE(2026,8,1)-1) | E17: =SUMIFS('Money Out'!F:F,'Money Out'!G:G,"Maintenance",'Money Out'!B:B,">="&DATE(2026,8,1),'Money Out'!B:B,"<="&DATE(2026,9,1)-1) | F17: =SUMIFS('Money Out'!F:F,'Money Out'!G:G,"Maintenance",'Money Out'!B:B,">="&DATE(2026,9,1),'Money Out'!B:B,"<="&DATE(2026,10,1)-1) | G17: =SUMIFS('Money Out'!F:F,'Money Out'!G:G,"Maintenance",'Money Out'!B:B,">="&DATE(2026,10,1),'Money Out'!B:B,"<="&DATE(2026,11,1)-1) | H17: =SUMIFS('Money Out'!F:F,'Money Out'!G:G,"Maintenance",'Money Out'!B:B,">="&DATE(2026,11,1),'Money Out'!B:B,"<="&DATE(2026,12,1)-1) | I17: =SUMIFS('Money Out'!F:F,'Money Out'!G:G,"Maintenance",'Money Out'!B:B,">="&DATE(2026,12,1),'Money Out'!B:B,"<="&DATE(2027,1,1)-1) | J17: =SUMIFS('Money Out'!F:F,'Money Out'!G:G,"Maintenance",'Money Out'!B:B,">="&DATE(2027,1,1),'Money Out'!B:B,"<="&DATE(2027,2,1)-1) | K17: =SUMIFS('Money Out'!F:F,'Money Out'!G:G,"Maintenance",'Money Out'!B:B,">="&DATE(2027,2,1),'Money Out'!B:B,"<="&DATE(2027,3,1)-1) | L17: =SUMIFS('Money Out'!F:F,'Money Out'!G:G,"Maintenance",'Money Out'!B:B,">="&DATE(2027,3,1),'Money Out'!B:B,"<="&DATE(2027,4,1)-1) | M17: =SUMIFS('Money Out'!F:F,'Money Out'!G:G,"Maintenance",'Money Out'!B:B,">="&DATE(2027,4,1),'Money Out'!B:B,"<="&DATE(2027,5,1)-1)
A18: Marketing | B18: =SUMIFS('Money Out'!F:F,'Money Out'!G:G,"Marketing",'Money Out'!B:B,">="&DATE(2026,5,1),'Money Out'!B:B,"<="&DATE(2026,6,1)-1) | C18: =SUMIFS('Money Out'!F:F,'Money Out'!G:G,"Marketing",'Money Out'!B:B,">="&DATE(2026,6,1),'Money Out'!B:B,"<="&DATE(2026,7,1)-1) | D18: =SUMIFS('Money Out'!F:F,'Money Out'!G:G,"Marketing",'Money Out'!B:B,">="&DATE(2026,7,1),'Money Out'!B:B,"<="&DATE(2026,8,1)-1) | E18: =SUMIFS('Money Out'!F:F,'Money Out'!G:G,"Marketing",'Money Out'!B:B,">="&DATE(2026,8,1),'Money Out'!B:B,"<="&DATE(2026,9,1)-1) | F18: =SUMIFS('Money Out'!F:F,'Money Out'!G:G,"Marketing",'Money Out'!B:B,">="&DATE(2026,9,1),'Money Out'!B:B,"<="&DATE(2026,10,1)-1) | G18: =SUMIFS('Money Out'!F:F,'Money Out'!G:G,"Marketing",'Money Out'!B:B,">="&DATE(2026,10,1),'Money Out'!B:B,"<="&DATE(2026,11,1)-1) | H18: =SUMIFS('Money Out'!F:F,'Money Out'!G:G,"Marketing",'Money Out'!B:B,">="&DATE(2026,11,1),'Money Out'!B:B,"<="&DATE(2026,12,1)-1) | I18: =SUMIFS('Money Out'!F:F,'Money Out'!G:G,"Marketing",'Money Out'!B:B,">="&DATE(2026,12,1),'Money Out'!B:B,"<="&DATE(2027,1,1)-1) | J18: =SUMIFS('Money Out'!F:F,'Money Out'!G:G,"Marketing",'Money Out'!B:B,">="&DATE(2027,1,1),'Money Out'!B:B,"<="&DATE(2027,2,1)-1) | K18: =SUMIFS('Money Out'!F:F,'Money Out'!G:G,"Marketing",'Money Out'!B:B,">="&DATE(2027,2,1),'Money Out'!B:B,"<="&DATE(2027,3,1)-1) | L18: =SUMIFS('Money Out'!F:F,'Money Out'!G:G,"Marketing",'Money Out'!B:B,">="&DATE(2027,3,1),'Money Out'!B:B,"<="&DATE(2027,4,1)-1) | M18: =SUMIFS('Money Out'!F:F,'Money Out'!G:G,"Marketing",'Money Out'!B:B,">="&DATE(2027,4,1),'Money Out'!B:B,"<="&DATE(2027,5,1)-1)
A19: Delivery | B19: =SUMIFS('Money Out'!F:F,'Money Out'!G:G,"Delivery (Porter/Dunzo)",'Money Out'!B:B,">="&DATE(2026,5,1),'Money Out'!B:B,"<="&DATE(2026,6,1)-1) | C19: =SUMIFS('Money Out'!F:F,'Money Out'!G:G,"Delivery (Porter/Dunzo)",'Money Out'!B:B,">="&DATE(2026,6,1),'Money Out'!B:B,"<="&DATE(2026,7,1)-1) | D19: =SUMIFS('Money Out'!F:F,'Money Out'!G:G,"Delivery (Porter/Dunzo)",'Money Out'!B:B,">="&DATE(2026,7,1),'Money Out'!B:B,"<="&DATE(2026,8,1)-1) | E19: =SUMIFS('Money Out'!F:F,'Money Out'!G:G,"Delivery (Porter/Dunzo)",'Money Out'!B:B,">="&DATE(2026,8,1),'Money Out'!B:B,"<="&DATE(2026,9,1)-1) | F19: =SUMIFS('Money Out'!F:F,'Money Out'!G:G,"Delivery (Porter/Dunzo)",'Money Out'!B:B,">="&DATE(2026,9,1),'Money Out'!B:B,"<="&DATE(2026,10,1)-1) | G19: =SUMIFS('Money Out'!F:F,'Money Out'!G:G,"Delivery (Porter/Dunzo)",'Money Out'!B:B,">="&DATE(2026,10,1),'Money Out'!B:B,"<="&DATE(2026,11,1)-1) | H19: =SUMIFS('Money Out'!F:F,'Money Out'!G:G,"Delivery (Porter/Dunzo)",'Money Out'!B:B,">="&DATE(2026,11,1),'Money Out'!B:B,"<="&DATE(2026,12,1)-1) | I19: =SUMIFS('Money Out'!F:F,'Money Out'!G:G,"Delivery (Porter/Dunzo)",'Money Out'!B:B,">="&DATE(2026,12,1),'Money Out'!B:B,"<="&DATE(2027,1,1)-1) | J19: =SUMIFS('Money Out'!F:F,'Money Out'!G:G,"Delivery (Porter/Dunzo)",'Money Out'!B:B,">="&DATE(2027,1,1),'Money Out'!B:B,"<="&DATE(2027,2,1)-1) | K19: =SUMIFS('Money Out'!F:F,'Money Out'!G:G,"Delivery (Porter/Dunzo)",'Money Out'!B:B,">="&DATE(2027,2,1),'Money Out'!B:B,"<="&DATE(2027,3,1)-1) | L19: =SUMIFS('Money Out'!F:F,'Money Out'!G:G,"Delivery (Porter/Dunzo)",'Money Out'!B:B,">="&DATE(2027,3,1),'Money Out'!B:B,"<="&DATE(2027,4,1)-1) | M19: =SUMIFS('Money Out'!F:F,'Money Out'!G:G,"Delivery (Porter/Dunzo)",'Money Out'!B:B,">="&DATE(2027,4,1),'Money Out'!B:B,"<="&DATE(2027,5,1)-1)
A20: Total opex | B20: =SUM(B15:B19) | C20: =SUM(C15:C19) | D20: =SUM(D15:D19) | E20: =SUM(E15:E19) | F20: =SUM(F15:F19) | G20: =SUM(G15:G19) | H20: =SUM(H15:H19) | I20: =SUM(I15:I19) | ... M20: =SUM(M15:M19)
A22: Operating profit | B22: =B11-B20 | C22: =C11-C20 | D22: =D11-D20 | E22: =E11-E20 | F22: =F11-F20 | G22: =G11-G20 | H22: =H11-H20 | I22: =I11-I20 | ... M22: =M11-M20
A24: BELOW THE LINE
A25: Capex | B25: =SUMIFS('Money Out'!F:F,'Money Out'!G:G,"Equipment (capex)",'Money Out'!B:B,">="&DATE(2026,5,1),'Money Out'!B:B,"<="&DATE(2026,6,1)-1) | C25: =SUMIFS('Money Out'!F:F,'Money Out'!G:G,"Equipment (capex)",'Money Out'!B:B,">="&DATE(2026,6,1),'Money Out'!B:B,"<="&DATE(2026,7,1)-1) | D25: =SUMIFS('Money Out'!F:F,'Money Out'!G:G,"Equipment (capex)",'Money Out'!B:B,">="&DATE(2026,7,1),'Money Out'!B:B,"<="&DATE(2026,8,1)-1) | E25: =SUMIFS('Money Out'!F:F,'Money Out'!G:G,"Equipment (capex)",'Money Out'!B:B,">="&DATE(2026,8,1),'Money Out'!B:B,"<="&DATE(2026,9,1)-1) | F25: =SUMIFS('Money Out'!F:F,'Money Out'!G:G,"Equipment (capex)",'Money Out'!B:B,">="&DATE(2026,9,1),'Money Out'!B:B,"<="&DATE(2026,10,1)-1) | G25: =SUMIFS('Money Out'!F:F,'Money Out'!G:G,"Equipment (capex)",'Money Out'!B:B,">="&DATE(2026,10,1),'Money Out'!B:B,"<="&DATE(2026,11,1)-1) | H25: =SUMIFS('Money Out'!F:F,'Money Out'!G:G,"Equipment (capex)",'Money Out'!B:B,">="&DATE(2026,11,1),'Money Out'!B:B,"<="&DATE(2026,12,1)-1) | I25: =SUMIFS('Money Out'!F:F,'Money Out'!G:G,"Equipment (capex)",'Money Out'!B:B,">="&DATE(2026,12,1),'Money Out'!B:B,"<="&DATE(2027,1,1)-1) | J25: =SUMIFS('Money Out'!F:F,'Money Out'!G:G,"Equipment (capex)",'Money Out'!B:B,">="&DATE(2027,1,1),'Money Out'!B:B,"<="&DATE(2027,2,1)-1) | K25: =SUMIFS('Money Out'!F:F,'Money Out'!G:G,"Equipment (capex)",'Money Out'!B:B,">="&DATE(2027,2,1),'Money Out'!B:B,"<="&DATE(2027,3,1)-1) | L25: =SUMIFS('Money Out'!F:F,'Money Out'!G:G,"Equipment (capex)",'Money Out'!B:B,">="&DATE(2027,3,1),'Money Out'!B:B,"<="&DATE(2027,4,1)-1) | M25: =SUMIFS('Money Out'!F:F,'Money Out'!G:G,"Equipment (capex)",'Money Out'!B:B,">="&DATE(2027,4,1),'Money Out'!B:B,"<="&DATE(2027,5,1)-1)
A26: Founder draws | B26: =SUMIFS('Money Out'!F:F,'Money Out'!G:G,"Founder Draw",'Money Out'!B:B,">="&DATE(2026,5,1),'Money Out'!B:B,"<="&DATE(2026,6,1)-1) | C26: =SUMIFS('Money Out'!F:F,'Money Out'!G:G,"Founder Draw",'Money Out'!B:B,">="&DATE(2026,6,1),'Money Out'!B:B,"<="&DATE(2026,7,1)-1) | D26: =SUMIFS('Money Out'!F:F,'Money Out'!G:G,"Founder Draw",'Money Out'!B:B,">="&DATE(2026,7,1),'Money Out'!B:B,"<="&DATE(2026,8,1)-1) | E26: =SUMIFS('Money Out'!F:F,'Money Out'!G:G,"Founder Draw",'Money Out'!B:B,">="&DATE(2026,8,1),'Money Out'!B:B,"<="&DATE(2026,9,1)-1) | F26: =SUMIFS('Money Out'!F:F,'Money Out'!G:G,"Founder Draw",'Money Out'!B:B,">="&DATE(2026,9,1),'Money Out'!B:B,"<="&DATE(2026,10,1)-1) | G26: =SUMIFS('Money Out'!F:F,'Money Out'!G:G,"Founder Draw",'Money Out'!B:B,">="&DATE(2026,10,1),'Money Out'!B:B,"<="&DATE(2026,11,1)-1) | H26: =SUMIFS('Money Out'!F:F,'Money Out'!G:G,"Founder Draw",'Money Out'!B:B,">="&DATE(2026,11,1),'Money Out'!B:B,"<="&DATE(2026,12,1)-1) | I26: =SUMIFS('Money Out'!F:F,'Money Out'!G:G,"Founder Draw",'Money Out'!B:B,">="&DATE(2026,12,1),'Money Out'!B:B,"<="&DATE(2027,1,1)-1) | J26: =SUMIFS('Money Out'!F:F,'Money Out'!G:G,"Founder Draw",'Money Out'!B:B,">="&DATE(2027,1,1),'Money Out'!B:B,"<="&DATE(2027,2,1)-1) | K26: =SUMIFS('Money Out'!F:F,'Money Out'!G:G,"Founder Draw",'Money Out'!B:B,">="&DATE(2027,2,1),'Money Out'!B:B,"<="&DATE(2027,3,1)-1) | L26: =SUMIFS('Money Out'!F:F,'Money Out'!G:G,"Founder Draw",'Money Out'!B:B,">="&DATE(2027,3,1),'Money Out'!B:B,"<="&DATE(2027,4,1)-1) | M26: =SUMIFS('Money Out'!F:F,'Money Out'!G:G,"Founder Draw",'Money Out'!B:B,">="&DATE(2027,4,1),'Money Out'!B:B,"<="&DATE(2027,5,1)-1)
A27: Net cash flow | B27: =B22-B25-B26 | C27: =C22-C25-C26 | D27: =D22-D25-D26 | E27: =E22-E25-E26 | F27: =F22-F25-F26 | G27: =G22-G25-G26 | H27: =H22-H25-H26 | I27: =I22-I25-I26 | ... M27: =M22-M25-M26

Sheet Cash Runway
A1: Month | B1: Opening cash (₹) | C1: Projected inflows (₹) | D1: Projected outflows (₹) | E1: Closing cash (₹) | F1: Runway flag | G1: Notes
A2: 2026-05 | B2: =SUM('Bank vs UPI Float'!F:F) | C2: 0 | D2: 0 | E2: =B2+C2-D2 | F2: =IF(E2<10000,"⚠ BELOW BUFFER",IF(E2<25000,"Tight","OK"))
A3: 2026-06 | B3: =E2 | C3: 0 | D3: 0 | E3: =B3+C3-D3 | F3: =IF(E3<10000,"⚠ BELOW BUFFER",IF(E3<25000,"Tight","OK"))
A4: 2026-07 | B4: =E3 | C4: 0 | D4: 0 | E4: =B4+C4-D4 | F4: =IF(E4<10000,"⚠ BELOW BUFFER",IF(E4<25000,"Tight","OK"))
A5: 2026-08 | B5: =E4 | C5: 0 | D5: 0 | E5: =B5+C5-D5 | F5: =IF(E5<10000,"⚠ BELOW BUFFER",IF(E5<25000,"Tight","OK"))
A6: 2026-09 | B6: =E5 | C6: 0 | D6: 0 | E6: =B6+C6-D6 | F6: =IF(E6<10000,"⚠ BELOW BUFFER",IF(E6<25000,"Tight","OK"))
A7: 2026-10 | B7: =E6 | C7: 0 | D7: 0 | E7: =B7+C7-D7 | F7: =IF(E7<10000,"⚠ BELOW BUFFER",IF(E7<25000,"Tight","OK"))
A8: 2026-11 | B8: =E7 | C8: 0 | D8: 0 | E8: =B8+C8-D8 | F8: =IF(E8<10000,"⚠ BELOW BUFFER",IF(E8<25000,"Tight","OK"))
A9: 2026-12 | B9: =E8 | C9: 0 | D9: 0 | E9: =B9+C9-D9 | F9: =IF(E9<10000,"⚠ BELOW BUFFER",IF(E9<25000,"Tight","OK"))
A10: 2027-01 | B10: =E9 | C10: 0 | D10: 0 | E10: =B10+C10-D10 | F10: =IF(E10<10000,"⚠ BELOW BUFFER",IF(E10<25000,"Tight","OK"))
A11: 2027-02 | B11: =E10 | C11: 0 | D11: 0 | E11: =B11+C11-D11 | F11: =IF(E11<10000,"⚠ BELOW BUFFER",IF(E11<25000,"Tight","OK"))
A12: 2027-03 | B12: =E11 | C12: 0 | D12: 0 | E12: =B12+C12-D12 | F12: =IF(E12<10000,"⚠ BELOW BUFFER",IF(E12<25000,"Tight","OK"))
A13: 2027-04 | B13: =E12 | C13: 0 | D13: 0 | E13: =B13+C13-D13 | F13: =IF(E13<10000,"⚠ BELOW BUFFER",IF(E13<25000,"Tight","OK"))

Sheet Capex Register
A1: Asset | B1: Category | C1: Purchased on | D1: Purchase price (₹) | E1: Supplier | F1: Linked Money Out ID | G1: Useful life (months) | H1: Monthly depreciation (₹) | I1: Net book value (₹) | J1: Notes
A2: Morphy Richards Besta Black 52 OTG | B2: Oven | C2: 45505 | D2: 0 | E2: (pre-existing equipment) | G2: 60 | H2: =IFERROR(D2/G2,"") | I2: =IFERROR(D2-(H2*MIN((TODAY()-C2)/30.4,G2)),"") | J2: Already owned. Zero capex but tracked for depreciation/replacement clock.
A3: KitchenAid 5KSM150 Stand Mixer | B3: Mixer | C3: 46154 | D3: 38000 | E3: KitchenAid India (Amazon) | F3: MOUT-0010 | G3: 36 | H3: =IFERROR(D3/G3,"") | I3: =IFERROR(D3-(H3*MIN((TODAY()-C3)/30.4,G3)),"") | J3: Replaces Philips hand mixer. 2-year warranty.
A4: Convection Oven (TBD — Borosil / Whirlpool) | B4: Oven | D4: 25000 | E4: (planned) | G4: 60 | H4: =IFERROR(D4/G4,"") | I4: =IFERROR(D4-(H4*MIN((TODAY()-C4)/30.4,G4)),"") | J4: Stream 1 evaluation pending. Phase 2 spend.
A5: Digital weighing scale 5kg | B5: Tools | C5: 46154 | D5: 1200 | E5: Amazon | G5: 36 | H5: =IFERROR(D5/G5,"") | I5: =IFERROR(D5-(H5*MIN((TODAY()-C5)/30.4,G5)),"") | J5: Precision needed for premium eggless. Bundled with mixer purchase.
A6: Cake turntables (×2) + offset spatulas (×3) | B6: Tools | C6: 46154 | D6: 1500 | E6: Amazon | G6: 24 | H6: =IFERROR(D6/G6,"") | I6: =IFERROR(D6-(H6*MIN((TODAY()-C6)/30.4,G6)),"") | J6: Standard decorating kit upgrade.
H7: =IFERROR(D7/G7,"") | I7: =IFERROR(D7-(H7*MIN((TODAY()-C7)/30.4,G7)),"")
H8: =IFERROR(D8/G8,"") | I8: =IFERROR(D8-(H8*MIN((TODAY()-C8)/30.4,G8)),"")
H9: =IFERROR(D9/G9,"") | I9: =IFERROR(D9-(H9*MIN((TODAY()-C9)/30.4,G9)),"")
H10: =IFERROR(D10/G10,"") | I10: =IFERROR(D10-(H10*MIN((TODAY()-C10)/30.4,G10)),"")
H11: =IFERROR(D11/G11,"") | I11: =IFERROR(D11-(H11*MIN((TODAY()-C11)/30.4,G11)),"")
H12: =IFERROR(D12/G12,"") | I12: =IFERROR(D12-(H12*MIN((TODAY()-C12)/30.4,G12)),"")
H13: =IFERROR(D13/G13,"") | I13: =IFERROR(D13-(H13*MIN((TODAY()-C13)/30.4,G13)),"")
H14: =IFERROR(D14/G14,"") | I14: =IFERROR(D14-(H14*MIN((TODAY()-C14)/30.4,G14)),"")
H15: =IFERROR(D15/G15,"") | I15: =IFERROR(D15-(H15*MIN((TODAY()-C15)/30.4,G15)),"")
H16: =IFERROR(D16/G16,"") | I16: =IFERROR(D16-(H16*MIN((TODAY()-C16)/30.4,G16)),"")
H17: =IFERROR(D17/G17,"") | I17: =IFERROR(D17-(H17*MIN((TODAY()-C17)/30.4,G17)),"")
H18: =IFERROR(D18/G18,"") | I18: =IFERROR(D18-(H18*MIN((TODAY()-C18)/30.4,G18)),"")
... H101: =IFERROR(D101/G101,"") | I101: =IFERROR(D101-(H101*MIN((TODAY()-C101)/30.4,G101)),"")

Sheet Founder Draws
A1: Date | B1: To | C1: Amount (₹) | D1: Purpose | E1: Linked Money Out ID | F1: Notes
A2: 46157 | B2: Swetha | C2: 15000 | D2: Salary | E2: MOUT-0011 | F2: May salary equivalent
A3: 46157 | B3: Shreya | C3: 15000 | D3: Salary | E3: MOUT-0012 | F3: May salary equivalent
A4: 46142 | B4: Joint | C4: 8000 | D4: Profit Distribution | F4: April surplus distribution; ₹4K each (logged jointly)
