Workbook

Sheet README
A1: Tiered Cake Company — CRM
A3: Owners: Swetha (S) · Shreya (Sh)
A4: Geography: Hyderabad (catchment: Eterna, Provincia, broader Financial District / Narsingi)
A5: Generated: 2026-05-24
A8: 1. IMPORT INTO GOOGLE SHEETS
A9: - Open https://sheets.google.com
A10: - File → Import → Upload → select this .xlsx → 'Replace spreadsheet'
A11: - All formulas, validations, and the 60-day capacity calendar carry across
A13: 2. SAMPLE DATA (highlighted yellow) is realistic but fictional
A14: - 10 customers across Rajapushpa Eterna and Rajapushpa Provincia
A15: - 10 orders (mix of delivered, in production, queued)
A16: - 8 inquiries (mix of New / Quoted / Confirmed / Lost)
... A44: Header row is dark; freeze panes set on row 1 of every tab.

Sheet Inquiries
A1: Inquiry ID | B1: Date received | C1: Channel | D1: Name | E1: Phone | F1: Occasion | G1: Event date | H1: What they want | I1: Budget hint | J1: Status | K1: Assigned to | L1: Quoted (₹) | M1: Notes | N1: Lost reason | O1: Consent (Y/N) | P1: Logged at | Q1: Customer ID (if promoted)
A2: =IF(B2="","","INQ-"&TEXT(ROW()-1,"0000")) | B2: 46165 | C2: Instagram | D2: Meera Joshi | E2: +919811001100 | F2: Birthday (kid) | G2: 46181 | H2: 2kg cake — Frozen / Elsa theme for daughter turning 6 | I2: ₹3500-4000 | J2: Quoted | K2: Shreya | L2: 3800 | M2: Lives in Provincia (Tower 7); referral from Lakshmi Nair | O2: Y | P2: =IF(B2="","",NOW())
A3: =IF(B3="","","INQ-"&TEXT(ROW()-1,"0000")) | B3: 46165 | C3: WhatsApp | D3: Tarun Saini | E3: +919822002200 | F3: Anniversary | G3: 46174 | H3: 1kg eggless chocolate cake; surprise for wife | I3: ~₹2000 | J3: Confirmed | K3: Shreya | L3: 2200 | M3: Eterna resident, Tower 3. Promote to Customers post-delivery. | O3: Y | P3: =IF(B3="","",NOW())
A4: =IF(B4="","","INQ-"&TEXT(ROW()-1,"0000")) | B4: 46164 | C4: WhatsApp | D4: Kavya Iyer | E4: +919833003300 | F4: Just Because | H4: Box of bomboloni — pistachio favourite | I4: ? | J4: New | K4: Shreya | M4: Friend of Arjun Mehta (CUS-0001). No event date — sometime in June | O4: N | P4: =IF(B4="","",NOW())
A5: =IF(B5="","","INQ-"&TEXT(ROW()-1,"0000")) | B5: 46163 | C5: Instagram | D5: Naveen Pillai | E5: +919844004400 | F5: Corporate | G5: 46188 | H5: 30 brownies + 30 cupcakes for office event (Cyberabad) | I5: ₹10000 ceiling | J5: Lost | K5: Shreya | L5: 9500 | M5: Wanted invoice with GST; we're not GST-registered yet. Lost on this. | N5: Other | O5: N | P5: =IF(B5="","",NOW())
A6: =IF(B6="","","INQ-"&TEXT(ROW()-1,"0000")) | B6: 46162 | C6: WhatsApp | D6: Pooja Bansal | E6: +919855005500 | F6: Birthday | G6: 46167 | H6: 1kg cake, eggless, any flavour | I6: <₹2000 | J6: Lost | K6: Shreya | M6: Date already full (Sunday). Politely declined; suggested next week. | N6: Date unavailable | O6: N | P6: =IF(B6="","",NOW())
A7: =IF(B7="","","INQ-"&TEXT(ROW()-1,"0000")) | B7: 46166 | C7: Referral | D7: Rajiv Khanna | E7: +919866006600 | F7: Wedding | G7: 46248 | H7: Multi-tier wedding cake — daughter's wedding in August | I7: ₹15000-25000 | J7: New | K7: Shreya | M7: BIG one. Provincia (Tower 9); referred by Anjali Agarwal. Site visit needed. | O7: Y | P7: =IF(B7="","",NOW())
A8: =IF(B8="","","INQ-"&TEXT(ROW()-1,"0000")) | B8: 46152 | C8: Referral | D8: Aditi Saxena | E8: +919877889900 | F8: Just Because | G8: 46173 | H8: Bomboloni box for dinner party | I8: ~₹1400 | J8: Confirmed | K8: Shreya | L8: 1400 | M8: Referred by Lakshmi Nair | O8: Y | P8: =IF(B8="","",NOW()) | Q8: CUS-0010
A9: =IF(B9="","","INQ-"&TEXT(ROW()-1,"0000")) | B9: 46160 | C9: Instagram | D9: Sneha Iyer | E9: +919822334455 | F9: Birthday | G9: 46164 | H9: 1kg eggless butterscotch — minimalist | I9: ₹2200 | J9: Confirmed | K9: Shreya | L9: 2200 | M9: First-time customer; husband initiated chat, Sneha is decision-maker | O9: Y | P9: =IF(B9="","",NOW()) | Q9: CUS-0008
A10: =IF(B10="","","INQ-"&TEXT(ROW()-1,"0000")) | P10: =IF(B10="","",NOW())
A11: =IF(B11="","","INQ-"&TEXT(ROW()-1,"0000")) | P11: =IF(B11="","",NOW())
A12: =IF(B12="","","INQ-"&TEXT(ROW()-1,"0000")) | P12: =IF(B12="","",NOW())
A13: =IF(B13="","","INQ-"&TEXT(ROW()-1,"0000")) | P13: =IF(B13="","",NOW())
A14: =IF(B14="","","INQ-"&TEXT(ROW()-1,"0000")) | P14: =IF(B14="","",NOW())
A15: =IF(B15="","","INQ-"&TEXT(ROW()-1,"0000")) | P15: =IF(B15="","",NOW())
A16: =IF(B16="","","INQ-"&TEXT(ROW()-1,"0000")) | P16: =IF(B16="","",NOW())
A17: =IF(B17="","","INQ-"&TEXT(ROW()-1,"0000")) | P17: =IF(B17="","",NOW())
A18: =IF(B18="","","INQ-"&TEXT(ROW()-1,"0000")) | P18: =IF(B18="","",NOW())
A19: =IF(B19="","","INQ-"&TEXT(ROW()-1,"0000")) | P19: =IF(B19="","",NOW())
A20: =IF(B20="","","INQ-"&TEXT(ROW()-1,"0000")) | P20: =IF(B20="","",NOW())
A21: =IF(B21="","","INQ-"&TEXT(ROW()-1,"0000")) | P21: =IF(B21="","",NOW())
... A201: =IF(B201="","","INQ-"&TEXT(ROW()-1,"0000")) | P201: =IF(B201="","",NOW())

Sheet Customers
A1: Customer ID | B1: Name | C1: Phone | D1: Email | E1: Address | F1: Dietary | G1: How they found us | H1: First order | I1: Last order | J1: Orders count | K1: Lifetime (₹) | L1: Marketing consent | M1: Consent date | N1: Notes
A2: CUS-0001 | B2: Arjun Mehta | C2: +919812345678 | D2: arjun.m@example.com | E2: Flat 1204, Tower 2, Rajapushpa Eterna, Nanakramguda, Financial District, Hyderabad 500032 | F2: Eggless preferred (Marwari household) | G2: WhatsApp | H2: 46040 | I2: =IFERROR(IF(MAXIFS(Orders!E:E,Orders!B:B,A2)=0,"",MAXIFS(Orders!E:E,Orders!B:B,A2)),"") | J2: =IF(A2="","",COUNTIF(Orders!B:B,A2)) | K2: =IF(A2="","",SUMIF(Orders!B:B,A2,Orders!K:K)) | L2: Y | M2: 46044 | N2: Two kids — Aanya (eggless cake fan), Veer (just turned 5)
A3: CUS-0002 | B3: Priya Reddy | C3: +919876543210 | D3: priya.r@example.com | E3: Flat 0708, Tower 5, Rajapushpa Provincia, Puppalaguda, Narsingi, Hyderabad 500075 | F3: Egg ok | G3: Instagram | H3: 46067 | I3: =IFERROR(IF(MAXIFS(Orders!E:E,Orders!B:B,A3)=0,"",MAXIFS(Orders!E:E,Orders!B:B,A3)),"") | J3: =IF(A3="","",COUNTIF(Orders!B:B,A3)) | K3: =IF(A3="","",SUMIF(Orders!B:B,A3,Orders!K:K)) | L3: Y | M3: 46071 | N3: Found us via Insta reel; kid Aarav's bday is the recurring trigger
A4: CUS-0003 | B4: Karthik Subramaniam | C4: +919900112233 | D4: karthik.s@example.com | E4: Flat 0502, Tower 1, Rajapushpa Eterna, Nanakramguda, Financial District, Hyderabad 500032 | F4: Egg ok; no nuts (wife allergy) | G4: Referral | H4: 45991 | I4: =IFERROR(IF(MAXIFS(Orders!E:E,Orders!B:B,A4)=0,"",MAXIFS(Orders!E:E,Orders!B:B,A4)),"") | J4: =IF(A4="","",COUNTIF(Orders!B:B,A4)) | K4: =IF(A4="","",SUMIF(Orders!B:B,A4,Orders!K:K)) | L4: Y | M4: 45994 | N4: Orders ~monthly; office celebrations + family events. Referred by Arjun.
A5: CUS-0004 | B5: Anjali Agarwal | C5: +919833221100 | D5: anjali.a@example.com | E5: Flat 2102, Tower 9, Rajapushpa Provincia, Puppalaguda, Narsingi, Hyderabad 500075 | F5: Strict eggless (Jain — no onion/garlic, but cakes ok) | G5: Instagram | H5: 46086 | I5: =IFERROR(IF(MAXIFS(Orders!E:E,Orders!B:B,A5)=0,"",MAXIFS(Orders!E:E,Orders!B:B,A5)),"") | J5: =IF(A5="","",COUNTIF(Orders!B:B,A5)) | K5: =IF(A5="","",SUMIF(Orders!B:B,A5,Orders!K:K)) | L5: Y | M5: 46091 | N5: High AOV; willing to pay for premium eggless. Two kids.
A6: CUS-0005 | B6: Rohan Kapoor | C6: +919944556677 | D6: rohan.k@example.com | E6: Flat 0904, Tower 3, Rajapushpa Eterna, Nanakramguda, Financial District, Hyderabad 500032 | F6: Egg ok | G6: WhatsApp | H6: 46019 | I6: =IFERROR(IF(MAXIFS(Orders!E:E,Orders!B:B,A6)=0,"",MAXIFS(Orders!E:E,Orders!B:B,A6)),"") | J6: =IF(A6="","",COUNTIF(Orders!B:B,A6)) | K6: =IF(A6="","",SUMIF(Orders!B:B,A6,Orders!K:K)) | L6: Y | M6: 46024 | N6: Anniversary always end-Dec; orders 1 day notice (chronic). Tip well.
A7: CUS-0006 | B7: Lakshmi Nair | C7: +919966778899 | D7: lakshmi.n@example.com | E7: Flat 0306, Tower 7, Rajapushpa Provincia, Puppalaguda, Narsingi, Hyderabad 500075 | F7: Egg ok | G7: Instagram | H7: 46124 | I7: =IFERROR(IF(MAXIFS(Orders!E:E,Orders!B:B,A7)=0,"",MAXIFS(Orders!E:E,Orders!B:B,A7)),"") | J7: =IF(A7="","",COUNTIF(Orders!B:B,A7)) | K7: =IF(A7="","",SUMIF(Orders!B:B,A7,Orders!K:K)) | L7: N | N7: Hasn't given marketing consent yet — only operational comms
A8: CUS-0007 | B8: Sandeep Goyal | C8: +919811223344 | D8: sandeep.g@example.com | E8: Flat 1801, Tower 4, Rajapushpa Provincia, Puppalaguda, Narsingi, Hyderabad 500075 | F8: Eggless only | G8: Referral | H8: 46075 | I8: =IFERROR(IF(MAXIFS(Orders!E:E,Orders!B:B,A8)=0,"",MAXIFS(Orders!E:E,Orders!B:B,A8)),"") | J8: =IF(A8="","",COUNTIF(Orders!B:B,A8)) | K8: =IF(A8="","",SUMIF(Orders!B:B,A8,Orders!K:K)) | L8: Y | M8: 46078 | N8: Bulk orders — Diwali gifting (50+ boxes last year). Anchor B2C-bulk relationship.
A9: CUS-0008 | B9: Sneha Iyer | C9: +919822334455 | D9: sneha.i@example.com | E9: Flat 0402, Tower 2, Rajapushpa Eterna, Nanakramguda, Financial District, Hyderabad 500032 | F9: Eggless preferred | G9: Instagram | H9: 46140 | I9: =IFERROR(IF(MAXIFS(Orders!E:E,Orders!B:B,A9)=0,"",MAXIFS(Orders!E:E,Orders!B:B,A9)),"") | J9: =IF(A9="","",COUNTIF(Orders!B:B,A9)) | K9: =IF(A9="","",SUMIF(Orders!B:B,A9,Orders!K:K)) | L9: Y | M9: 46143 | N9: Husband orders; she's the decision-maker. Bday is May 30.
A10: CUS-0009 | B10: Vikram Bhatia | C10: +919855667788 | D10: vikram.b@example.com | E10: Flat 1503, Tower 6, Rajapushpa Provincia, Puppalaguda, Narsingi, Hyderabad 500075 | F10: Egg ok | G10: WhatsApp | H10: 46099 | I10: =IFERROR(IF(MAXIFS(Orders!E:E,Orders!B:B,A10)=0,"",MAXIFS(Orders!E:E,Orders!B:B,A10)),"") | J10: =IF(A10="","",COUNTIF(Orders!B:B,A10)) | K10: =IF(A10="","",SUMIF(Orders!B:B,A10,Orders!K:K)) | L10: Y | M10: 46101 | N10: Punjabi household; loves rich chocolate. Two kids + anniversary.
A11: CUS-0010 | B11: Aditi Saxena | C11: +919877889900 | D11: aditi.s@example.com | E11: Flat 1106, Tower 8, Rajapushpa Provincia, Puppalaguda, Narsingi, Hyderabad 500075 | F11: Egg ok | G11: Referral | H11: 46152 | I11: =IFERROR(IF(MAXIFS(Orders!E:E,Orders!B:B,A11)=0,"",MAXIFS(Orders!E:E,Orders!B:B,A11)),"") | J11: =IF(A11="","",COUNTIF(Orders!B:B,A11)) | K11: =IF(A11="","",SUMIF(Orders!B:B,A11,Orders!K:K)) | L11: Y | M11: 46154 | N11: Referred Lakshmi Nair; potential repeat referrer — treat well
I12: =IFERROR(IF(MAXIFS(Orders!E:E,Orders!B:B,A12)=0,"",MAXIFS(Orders!E:E,Orders!B:B,A12)),"") | J12: =IF(A12="","",COUNTIF(Orders!B:B,A12)) | K12: =IF(A12="","",SUMIF(Orders!B:B,A12,Orders!K:K))
I13: =IFERROR(IF(MAXIFS(Orders!E:E,Orders!B:B,A13)=0,"",MAXIFS(Orders!E:E,Orders!B:B,A13)),"") | J13: =IF(A13="","",COUNTIF(Orders!B:B,A13)) | K13: =IF(A13="","",SUMIF(Orders!B:B,A13,Orders!K:K))
I14: =IFERROR(IF(MAXIFS(Orders!E:E,Orders!B:B,A14)=0,"",MAXIFS(Orders!E:E,Orders!B:B,A14)),"") | J14: =IF(A14="","",COUNTIF(Orders!B:B,A14)) | K14: =IF(A14="","",SUMIF(Orders!B:B,A14,Orders!K:K))
I15: =IFERROR(IF(MAXIFS(Orders!E:E,Orders!B:B,A15)=0,"",MAXIFS(Orders!E:E,Orders!B:B,A15)),"") | J15: =IF(A15="","",COUNTIF(Orders!B:B,A15)) | K15: =IF(A15="","",SUMIF(Orders!B:B,A15,Orders!K:K))
I16: =IFERROR(IF(MAXIFS(Orders!E:E,Orders!B:B,A16)=0,"",MAXIFS(Orders!E:E,Orders!B:B,A16)),"") | J16: =IF(A16="","",COUNTIF(Orders!B:B,A16)) | K16: =IF(A16="","",SUMIF(Orders!B:B,A16,Orders!K:K))
I17: =IFERROR(IF(MAXIFS(Orders!E:E,Orders!B:B,A17)=0,"",MAXIFS(Orders!E:E,Orders!B:B,A17)),"") | J17: =IF(A17="","",COUNTIF(Orders!B:B,A17)) | K17: =IF(A17="","",SUMIF(Orders!B:B,A17,Orders!K:K))
I18: =IFERROR(IF(MAXIFS(Orders!E:E,Orders!B:B,A18)=0,"",MAXIFS(Orders!E:E,Orders!B:B,A18)),"") | J18: =IF(A18="","",COUNTIF(Orders!B:B,A18)) | K18: =IF(A18="","",SUMIF(Orders!B:B,A18,Orders!K:K))
I19: =IFERROR(IF(MAXIFS(Orders!E:E,Orders!B:B,A19)=0,"",MAXIFS(Orders!E:E,Orders!B:B,A19)),"") | J19: =IF(A19="","",COUNTIF(Orders!B:B,A19)) | K19: =IF(A19="","",SUMIF(Orders!B:B,A19,Orders!K:K))
I20: =IFERROR(IF(MAXIFS(Orders!E:E,Orders!B:B,A20)=0,"",MAXIFS(Orders!E:E,Orders!B:B,A20)),"") | J20: =IF(A20="","",COUNTIF(Orders!B:B,A20)) | K20: =IF(A20="","",SUMIF(Orders!B:B,A20,Orders!K:K))
I21: =IFERROR(IF(MAXIFS(Orders!E:E,Orders!B:B,A21)=0,"",MAXIFS(Orders!E:E,Orders!B:B,A21)),"") | J21: =IF(A21="","",COUNTIF(Orders!B:B,A21)) | K21: =IF(A21="","",SUMIF(Orders!B:B,A21,Orders!K:K))
I22: =IFERROR(IF(MAXIFS(Orders!E:E,Orders!B:B,A22)=0,"",MAXIFS(Orders!E:E,Orders!B:B,A22)),"") | J22: =IF(A22="","",COUNTIF(Orders!B:B,A22)) | K22: =IF(A22="","",SUMIF(Orders!B:B,A22,Orders!K:K))
I23: =IFERROR(IF(MAXIFS(Orders!E:E,Orders!B:B,A23)=0,"",MAXIFS(Orders!E:E,Orders!B:B,A23)),"") | J23: =IF(A23="","",COUNTIF(Orders!B:B,A23)) | K23: =IF(A23="","",SUMIF(Orders!B:B,A23,Orders!K:K))
... I501: =IFERROR(IF(MAXIFS(Orders!E:E,Orders!B:B,A501)=0,"",MAXIFS(Orders!E:E,Orders!B:B,A501)),"") | J501: =IF(A501="","",COUNTIF(Orders!B:B,A501)) | K501: =IF(A501="","",SUMIF(Orders!B:B,A501,Orders!K:K))

Sheet Orders
A1: Order ID | B1: Customer ID | C1: Name (auto) | D1: Order date | E1: Delivery date | F1: Product | G1: Flavour | H1: Size / Qty | I1: Customisation | J1: Quoted (₹) | K1: Final (₹) | L1: Deposit received (₹) | M1: Balance received (₹) | N1: Balance due (₹) | O1: Payment mode | P1: Delivery mode | Q1: Cold-chain notes | R1: UPI reference (UTR) | S1: Payer VPA | T1: Production | U1: Delivery | V1: Feedback received | W1: Rating | X1: Feedback | Y1: Invoice ID | Z1: Notes
A2: =IF(B2="","","ORD-"&TEXT(ROW()-1,"0000")) | B2: CUS-0001 | C2: =IFERROR(VLOOKUP(B2,Customers!A:B,2,FALSE),"") | D2: 46040 | E2: 46044 | F2: Cake | G2: Eggless dark chocolate | H2: 1.5kg | I2: Dinosaur theme for Veer's 5th — green/blue fondant | J2: 2800 | K2: 2800 | L2: 1400 | M2: 1400 | N2: =IF(K2="","",K2-IFERROR(L2,0)-IFERROR(M2,0)) | O2: UPI | P2: Own delivery | Q2: Delivered 10am — Hyderabad winter, no cold-chain concern | R2: 422118203341 | S2: arjun.mehta@oksbi | T2: Done | U2: Delivered | V2: Y | W2: 5 | X2: Veer wouldn't stop talking about it. Will reorder. | Z2: First order
A3: =IF(B3="","","ORD-"&TEXT(ROW()-1,"0000")) | B3: CUS-0002 | C3: =IFERROR(VLOOKUP(B3,Customers!A:B,2,FALSE),"") | D3: 46067 | E3: 46069 | F3: Cupcakes | G3: Red velvet with cream cheese | H3: 12 (1 dozen) | I3: Heart-shape liners; gold sprinkles for Valentine's | J3: 1500 | K3: 1500 | L3: 500 | M3: 1000 | N3: =IF(K3="","",K3-IFERROR(L3,0)-IFERROR(M3,0)) | O3: UPI | P3: Customer pickup | Q3: Picked up by Priya herself at 9:30am | R3: 431229104852 | S3: priya.r@okhdfcbank | T3: Done | U3: Delivered | V3: Y | W3: 5 | X3: Beautifully done!
A4: =IF(B4="","","ORD-"&TEXT(ROW()-1,"0000")) | B4: CUS-0003 | C4: =IFERROR(VLOOKUP(B4,Customers!A:B,2,FALSE),"") | D4: 45991 | E4: 45993 | F4: Cake | G4: Pineapple sponge | H4: 1kg | I4: Office anniversary cake — 'Cordant 11 yrs' topper | J4: 2000 | K4: 2000 | L4: 0 | M4: 2000 | N4: =IF(K4="","",K4-IFERROR(L4,0)-IFERROR(M4,0)) | O4: Bank Transfer | P4: Porter | Q4: Porter at 4pm; office address Salarpuria Sattva Knowledge City | R4: 4321XXXX5678 | S4: bank-transfer | T4: Done | U4: Delivered | V4: Y | W4: 4 | X4: Sponge a bit dense — feedback noted | Z4: Office order
A5: =IF(B5="","","ORD-"&TEXT(ROW()-1,"0000")) | B5: CUS-0004 | C5: =IFERROR(VLOOKUP(B5,Customers!A:B,2,FALSE),"") | D5: 46086 | E5: 46090 | F5: Cake | G5: Jain eggless red velvet | H5: 2kg | I5: Unicorn theme for daughter Myra's 6th; pastel pink/purple; no fondant figures | J5: 4500 | K5: 4500 | L5: 2000 | M5: 2500 | N5: =IF(K5="","",K5-IFERROR(L5,0)-IFERROR(M5,0)) | O5: UPI | P5: Own delivery | Q5: Insulated box + 4 ice packs; Provincia to Eterna route, ~12 min | R5: 445533781290 | S5: anjali.a@okaxis | T5: Done | U5: Delivered | V5: Y | W5: 5 | X5: Worth every rupee. Eggless and still rich. | Z5: Premium order — repeat likely
A6: =IF(B6="","","ORD-"&TEXT(ROW()-1,"0000")) | B6: CUS-0005 | C6: =IFERROR(VLOOKUP(B6,Customers!A:B,2,FALSE),"") | D6: 46019 | E6: 46020 | F6: Cake | G6: Chocolate truffle | H6: 1kg | I6: Anniversary — 'R & N — 8 years' message | J6: 1800 | K6: 1800 | L6: 0 | M6: 1800 | N6: =IF(K6="","",K6-IFERROR(L6,0)-IFERROR(M6,0)) | O6: UPI | P6: Own delivery | Q6: Same-day winter delivery, no issues | R6: 449988102345 | S6: rohan.k@okicici | T6: Done | U6: Delivered | V6: N | Z6: Rush job (1-day notice) — fine because winter
A7: =IF(B7="","","ORD-"&TEXT(ROW()-1,"0000")) | B7: CUS-0007 | C7: =IFERROR(VLOOKUP(B7,Customers!A:B,2,FALSE),"") | D7: 46156 | E7: 46160 | F7: Cake Tub | G7: Tiramisu + Biscoff mix | H7: 6 tubs (assorted) | I7: Trial run before Diwali bulk order — Sandeep evaluating quality | J7: 3000 | K7: 3000 | L7: 1500 | M7: 1500 | N7: =IF(K7="","",K7-IFERROR(L7,0)-IFERROR(M7,0)) | O7: UPI | P7: Own delivery | Q7: Tubs delivered cold; insulated bag + 2 ice packs | R7: 520011445566 | S7: sandeep.g@okhdfcbank | T7: Done | U7: Delivered | V7: Y | W7: 5 | X7: Tiramisu nailed it. Let's plan Diwali boxes. | Z7: Diwali pipeline trigger
A8: =IF(B8="","","ORD-"&TEXT(ROW()-1,"0000")) | B8: CUS-0008 | C8: =IFERROR(VLOOKUP(B8,Customers!A:B,2,FALSE),"") | D8: 46160 | E8: 46164 | F8: Cake | G8: Eggless butterscotch | H8: 1kg | I8: Sneha's birthday — minimalist gold + white, no piping figures | J8: 2200 | K8: 2200 | L8: 1100 | M8: 1100 | N8: =IF(K8="","",K8-IFERROR(L8,0)-IFERROR(M8,0)) | O8: UPI | P8: Own delivery | Q8: Pickup before 11am — Hyderabad summer, 38°C forecast | R8: 521122876543 | S8: sneha.i@oksbi | T8: Done | U8: Delivered | V8: N | Z8: T+2 feedback request due today
A9: =IF(B9="","","ORD-"&TEXT(ROW()-1,"0000")) | B9: CUS-0009 | C9: =IFERROR(VLOOKUP(B9,Customers!A:B,2,FALSE),"") | D9: 46164 | E9: 46169 | F9: Cake | G9: Chocolate hazelnut | H9: 2kg | I9: Vikram & wife's 10th anniversary — gold drip, photo on top | J9: 3500 | K9: 3500 | L9: 1500 | M9: 0 | N9: =IF(K9="","",K9-IFERROR(L9,0)-IFERROR(M9,0)) | O9: UPI | P9: Own delivery | Q9: Will be 39°C; insulated + ice packs; AM slot booked | R9: 522233998877 | S9: vikram.b@okhdfcbank | T9: Decorate | U9: Pending | V9: N | Z9: Photo edible-print to source by 25 May
A10: =IF(B10="","","ORD-"&TEXT(ROW()-1,"0000")) | B10: CUS-0002 | C10: =IFERROR(VLOOKUP(B10,Customers!A:B,2,FALSE),"") | D10: 46165 | E10: 46172 | F10: Cake | G10: Eggless chocolate | H10: 2kg | I10: Aarav (kid) turning 7 — Spider-Man theme; red/blue fondant | J10: 3200 | K10: 3200 | L10: 1500 | M10: 0 | N10: =IF(K10="","",K10-IFERROR(L10,0)-IFERROR(M10,0)) | O10: UPI | P10: Own delivery | Q10: Saturday morning slot — heat, insulated box mandatory | R10: 522288554433 | S10: priya.r@okhdfcbank | T10: Queued | U10: Pending | V10: N
A11: =IF(B11="","","ORD-"&TEXT(ROW()-1,"0000")) | B11: CUS-0010 | C11: =IFERROR(VLOOKUP(B11,Customers!A:B,2,FALSE),"") | D11: 46164 | E11: 46173 | F11: Bomboloni | G11: Pistachio + Nutella (mixed box) | H11: 12 (1 box of 12) | I11: Dinner-party box; Saturday evening pickup | J11: 1400 | K11: 1400 | L11: 700 | M11: 0 | N11: =IF(K11="","",K11-IFERROR(L11,0)-IFERROR(M11,0)) | O11: UPI | P11: Customer pickup | Q11: Pickup at 6pm; bomboloni hold 4h boxed | R11: 523344112266 | S11: aditi.s@oksbi | T11: Queued | U11: Pending | V11: N | Z11: Aditi's first order
A12: =IF(B12="","","ORD-"&TEXT(ROW()-1,"0000")) | C12: =IFERROR(VLOOKUP(B12,Customers!A:B,2,FALSE),"") | N12: =IF(K12="","",K12-IFERROR(L12,0)-IFERROR(M12,0))
A13: =IF(B13="","","ORD-"&TEXT(ROW()-1,"0000")) | C13: =IFERROR(VLOOKUP(B13,Customers!A:B,2,FALSE),"") | N13: =IF(K13="","",K13-IFERROR(L13,0)-IFERROR(M13,0))
A14: =IF(B14="","","ORD-"&TEXT(ROW()-1,"0000")) | C14: =IFERROR(VLOOKUP(B14,Customers!A:B,2,FALSE),"") | N14: =IF(K14="","",K14-IFERROR(L14,0)-IFERROR(M14,0))
A15: =IF(B15="","","ORD-"&TEXT(ROW()-1,"0000")) | C15: =IFERROR(VLOOKUP(B15,Customers!A:B,2,FALSE),"") | N15: =IF(K15="","",K15-IFERROR(L15,0)-IFERROR(M15,0))
A16: =IF(B16="","","ORD-"&TEXT(ROW()-1,"0000")) | C16: =IFERROR(VLOOKUP(B16,Customers!A:B,2,FALSE),"") | N16: =IF(K16="","",K16-IFERROR(L16,0)-IFERROR(M16,0))
A17: =IF(B17="","","ORD-"&TEXT(ROW()-1,"0000")) | C17: =IFERROR(VLOOKUP(B17,Customers!A:B,2,FALSE),"") | N17: =IF(K17="","",K17-IFERROR(L17,0)-IFERROR(M17,0))
A18: =IF(B18="","","ORD-"&TEXT(ROW()-1,"0000")) | C18: =IFERROR(VLOOKUP(B18,Customers!A:B,2,FALSE),"") | N18: =IF(K18="","",K18-IFERROR(L18,0)-IFERROR(M18,0))
A19: =IF(B19="","","ORD-"&TEXT(ROW()-1,"0000")) | C19: =IFERROR(VLOOKUP(B19,Customers!A:B,2,FALSE),"") | N19: =IF(K19="","",K19-IFERROR(L19,0)-IFERROR(M19,0))
A20: =IF(B20="","","ORD-"&TEXT(ROW()-1,"0000")) | C20: =IFERROR(VLOOKUP(B20,Customers!A:B,2,FALSE),"") | N20: =IF(K20="","",K20-IFERROR(L20,0)-IFERROR(M20,0))
A21: =IF(B21="","","ORD-"&TEXT(ROW()-1,"0000")) | C21: =IFERROR(VLOOKUP(B21,Customers!A:B,2,FALSE),"") | N21: =IF(K21="","",K21-IFERROR(L21,0)-IFERROR(M21,0))
A22: =IF(B22="","","ORD-"&TEXT(ROW()-1,"0000")) | C22: =IFERROR(VLOOKUP(B22,Customers!A:B,2,FALSE),"") | N22: =IF(K22="","",K22-IFERROR(L22,0)-IFERROR(M22,0))
A23: =IF(B23="","","ORD-"&TEXT(ROW()-1,"0000")) | C23: =IFERROR(VLOOKUP(B23,Customers!A:B,2,FALSE),"") | N23: =IF(K23="","",K23-IFERROR(L23,0)-IFERROR(M23,0))
... A501: =IF(B501="","","ORD-"&TEXT(ROW()-1,"0000")) | C501: =IFERROR(VLOOKUP(B501,Customers!A:B,2,FALSE),"") | N501: =IF(K501="","",K501-IFERROR(L501,0)-IFERROR(M501,0))

Sheet Occasions
A1: Occasion ID | B1: Customer ID | C1: Name (auto) | D1: Type | E1: Month-Day (MM-DD) | F1: Year first known | G1: For whom | H1: Notes | I1: Consent (auto)
A2: =IF(B2="","","OCC-"&TEXT(ROW()-1,"0000")) | B2: CUS-0001 | C2: =IFERROR(VLOOKUP(B2,Customers!A:B,2,FALSE),"") | D2: Birthday (kid) | E2: 08-14 | F2: 2019 | G2: Aanya (daughter, turns 7 in 2026) | H2: Eggless mandatory; loves unicorns and pastels | I2: =IFERROR(VLOOKUP(B2,Customers!A:L,12,FALSE),"")
A3: =IF(B3="","","OCC-"&TEXT(ROW()-1,"0000")) | B3: CUS-0001 | C3: =IFERROR(VLOOKUP(B3,Customers!A:B,2,FALSE),"") | D3: Birthday (kid) | E3: 01-22 | F3: 2021 | G3: Veer (son, turned 5 in 2026) | H3: Dinosaur fan; dark chocolate fine | I3: =IFERROR(VLOOKUP(B3,Customers!A:L,12,FALSE),"")
A4: =IF(B4="","","OCC-"&TEXT(ROW()-1,"0000")) | B4: CUS-0001 | C4: =IFERROR(VLOOKUP(B4,Customers!A:B,2,FALSE),"") | D4: Anniversary | E4: 11-12 | F4: 2017 | G4: Arjun & Tanya | I4: =IFERROR(VLOOKUP(B4,Customers!A:L,12,FALSE),"")
A5: =IF(B5="","","OCC-"&TEXT(ROW()-1,"0000")) | B5: CUS-0002 | C5: =IFERROR(VLOOKUP(B5,Customers!A:B,2,FALSE),"") | D5: Birthday (kid) | E5: 05-30 | F5: 2019 | G5: Aarav (son, turning 7) | H5: Theme changes yearly — confirm 2 wks before | I5: =IFERROR(VLOOKUP(B5,Customers!A:L,12,FALSE),"")
A6: =IF(B6="","","OCC-"&TEXT(ROW()-1,"0000")) | B6: CUS-0002 | C6: =IFERROR(VLOOKUP(B6,Customers!A:B,2,FALSE),"") | D6: Birthday (self) | E6: 10-04 | F6: 1989 | G6: Priya | I6: =IFERROR(VLOOKUP(B6,Customers!A:L,12,FALSE),"")
A7: =IF(B7="","","OCC-"&TEXT(ROW()-1,"0000")) | B7: CUS-0003 | C7: =IFERROR(VLOOKUP(B7,Customers!A:B,2,FALSE),"") | D7: Anniversary | E7: 12-02 | F7: 2014 | G7: Karthik & Meghna | H7: Office cake annual tradition | I7: =IFERROR(VLOOKUP(B7,Customers!A:L,12,FALSE),"")
A8: =IF(B8="","","OCC-"&TEXT(ROW()-1,"0000")) | B8: CUS-0004 | C8: =IFERROR(VLOOKUP(B8,Customers!A:B,2,FALSE),"") | D8: Birthday (kid) | E8: 03-09 | F8: 2020 | G8: Myra (daughter, turned 6) | H8: Jain eggless; no fondant figures | I8: =IFERROR(VLOOKUP(B8,Customers!A:L,12,FALSE),"")
A9: =IF(B9="","","OCC-"&TEXT(ROW()-1,"0000")) | B9: CUS-0004 | C9: =IFERROR(VLOOKUP(B9,Customers!A:B,2,FALSE),"") | D9: Birthday (kid) | E9: 09-21 | F9: 2022 | G9: Krish (son, turning 4) | I9: =IFERROR(VLOOKUP(B9,Customers!A:L,12,FALSE),"")
A10: =IF(B10="","","OCC-"&TEXT(ROW()-1,"0000")) | B10: CUS-0005 | C10: =IFERROR(VLOOKUP(B10,Customers!A:B,2,FALSE),"") | D10: Anniversary | E10: 12-29 | F10: 2017 | G10: Rohan & Nisha | H10: Always last-minute (1-day notice) | I10: =IFERROR(VLOOKUP(B10,Customers!A:L,12,FALSE),"")
A11: =IF(B11="","","OCC-"&TEXT(ROW()-1,"0000")) | B11: CUS-0007 | C11: =IFERROR(VLOOKUP(B11,Customers!A:B,2,FALSE),"") | D11: Diwali bulk | E11: 11-01 | F11: 2025 | G11: Sandeep — corporate gifting | H11: 50+ assorted boxes; lock production calendar 3 wks ahead | I11: =IFERROR(VLOOKUP(B11,Customers!A:L,12,FALSE),"")
A12: =IF(B12="","","OCC-"&TEXT(ROW()-1,"0000")) | B12: CUS-0008 | C12: =IFERROR(VLOOKUP(B12,Customers!A:B,2,FALSE),"") | D12: Birthday (self) | E12: 05-30 | F12: 1988 | G12: Sneha | H12: Eggless preferred | I12: =IFERROR(VLOOKUP(B12,Customers!A:L,12,FALSE),"")
A13: =IF(B13="","","OCC-"&TEXT(ROW()-1,"0000")) | B13: CUS-0009 | C13: =IFERROR(VLOOKUP(B13,Customers!A:B,2,FALSE),"") | D13: Anniversary | E13: 05-27 | F13: 2016 | G13: Vikram & Ria | H13: Photo edible-print preferred | I13: =IFERROR(VLOOKUP(B13,Customers!A:L,12,FALSE),"")
A14: =IF(B14="","","OCC-"&TEXT(ROW()-1,"0000")) | B14: CUS-0009 | C14: =IFERROR(VLOOKUP(B14,Customers!A:B,2,FALSE),"") | D14: Birthday (kid) | E14: 07-19 | F14: 2018 | G14: Aria (daughter, turning 8) | I14: =IFERROR(VLOOKUP(B14,Customers!A:L,12,FALSE),"")
A15: =IF(B15="","","OCC-"&TEXT(ROW()-1,"0000")) | B15: CUS-0010 | C15: =IFERROR(VLOOKUP(B15,Customers!A:B,2,FALSE),"") | D15: Birthday (self) | E15: 11-23 | F15: 1991 | G15: Aditi | I15: =IFERROR(VLOOKUP(B15,Customers!A:L,12,FALSE),"")
A16: =IF(B16="","","OCC-"&TEXT(ROW()-1,"0000")) | C16: =IFERROR(VLOOKUP(B16,Customers!A:B,2,FALSE),"") | I16: =IFERROR(VLOOKUP(B16,Customers!A:L,12,FALSE),"")
A17: =IF(B17="","","OCC-"&TEXT(ROW()-1,"0000")) | C17: =IFERROR(VLOOKUP(B17,Customers!A:B,2,FALSE),"") | I17: =IFERROR(VLOOKUP(B17,Customers!A:L,12,FALSE),"")
A18: =IF(B18="","","OCC-"&TEXT(ROW()-1,"0000")) | C18: =IFERROR(VLOOKUP(B18,Customers!A:B,2,FALSE),"") | I18: =IFERROR(VLOOKUP(B18,Customers!A:L,12,FALSE),"")
A19: =IF(B19="","","OCC-"&TEXT(ROW()-1,"0000")) | C19: =IFERROR(VLOOKUP(B19,Customers!A:B,2,FALSE),"") | I19: =IFERROR(VLOOKUP(B19,Customers!A:L,12,FALSE),"")
A20: =IF(B20="","","OCC-"&TEXT(ROW()-1,"0000")) | C20: =IFERROR(VLOOKUP(B20,Customers!A:B,2,FALSE),"") | I20: =IFERROR(VLOOKUP(B20,Customers!A:L,12,FALSE),"")
A21: =IF(B21="","","OCC-"&TEXT(ROW()-1,"0000")) | C21: =IFERROR(VLOOKUP(B21,Customers!A:B,2,FALSE),"") | I21: =IFERROR(VLOOKUP(B21,Customers!A:L,12,FALSE),"")
A22: =IF(B22="","","OCC-"&TEXT(ROW()-1,"0000")) | C22: =IFERROR(VLOOKUP(B22,Customers!A:B,2,FALSE),"") | I22: =IFERROR(VLOOKUP(B22,Customers!A:L,12,FALSE),"")
A23: =IF(B23="","","OCC-"&TEXT(ROW()-1,"0000")) | C23: =IFERROR(VLOOKUP(B23,Customers!A:B,2,FALSE),"") | I23: =IFERROR(VLOOKUP(B23,Customers!A:L,12,FALSE),"")
A24: =IF(B24="","","OCC-"&TEXT(ROW()-1,"0000")) | C24: =IFERROR(VLOOKUP(B24,Customers!A:B,2,FALSE),"") | I24: =IFERROR(VLOOKUP(B24,Customers!A:L,12,FALSE),"")
A25: =IF(B25="","","OCC-"&TEXT(ROW()-1,"0000")) | C25: =IFERROR(VLOOKUP(B25,Customers!A:B,2,FALSE),"") | I25: =IFERROR(VLOOKUP(B25,Customers!A:L,12,FALSE),"")
A26: =IF(B26="","","OCC-"&TEXT(ROW()-1,"0000")) | C26: =IFERROR(VLOOKUP(B26,Customers!A:B,2,FALSE),"") | I26: =IFERROR(VLOOKUP(B26,Customers!A:L,12,FALSE),"")
A27: =IF(B27="","","OCC-"&TEXT(ROW()-1,"0000")) | C27: =IFERROR(VLOOKUP(B27,Customers!A:B,2,FALSE),"") | I27: =IFERROR(VLOOKUP(B27,Customers!A:L,12,FALSE),"")
... A501: =IF(B501="","","OCC-"&TEXT(ROW()-1,"0000")) | C501: =IFERROR(VLOOKUP(B501,Customers!A:B,2,FALSE),"") | I501: =IFERROR(VLOOKUP(B501,Customers!A:L,12,FALSE),"")

Sheet Capacity Calendar
A1: Date | B1: Day | C1: Cake slots (total) | D1: Cake slots (used) | E1: Cupcake dozens (total) | F1: Cupcake dozens (used) | G1: Bomboloni batches (total) | H1: Bomboloni batches (used) | I1: Blocked | J1: Block reason | K1: Utilisation % | L1: Notes
A2: 46166 | B2: =TEXT(A2,"ddd") | C2: 5 | D2: =COUNTIFS(Orders!E:E,A2,Orders!F:F,"Cake") | E2: 4 | F2: =COUNTIFS(Orders!E:E,A2,Orders!F:F,"Cupcakes") | G2: 1 | H2: =COUNTIFS(Orders!E:E,A2,Orders!F:F,"Bomboloni") | I2: N | K2: =IFERROR((D2/C2+F2/E2+H2/G2)/3,0)
A3: 46167 | B3: =TEXT(A3,"ddd") | C3: 3 | D3: =COUNTIFS(Orders!E:E,A3,Orders!F:F,"Cake") | E3: 4 | F3: =COUNTIFS(Orders!E:E,A3,Orders!F:F,"Cupcakes") | G3: 1 | H3: =COUNTIFS(Orders!E:E,A3,Orders!F:F,"Bomboloni") | I3: N | K3: =IFERROR((D3/C3+F3/E3+H3/G3)/3,0)
A4: 46168 | B4: =TEXT(A4,"ddd") | C4: 3 | D4: =COUNTIFS(Orders!E:E,A4,Orders!F:F,"Cake") | E4: 4 | F4: =COUNTIFS(Orders!E:E,A4,Orders!F:F,"Cupcakes") | G4: 1 | H4: =COUNTIFS(Orders!E:E,A4,Orders!F:F,"Bomboloni") | I4: N | K4: =IFERROR((D4/C4+F4/E4+H4/G4)/3,0)
A5: 46169 | B5: =TEXT(A5,"ddd") | C5: 3 | D5: =COUNTIFS(Orders!E:E,A5,Orders!F:F,"Cake") | E5: 4 | F5: =COUNTIFS(Orders!E:E,A5,Orders!F:F,"Cupcakes") | G5: 1 | H5: =COUNTIFS(Orders!E:E,A5,Orders!F:F,"Bomboloni") | I5: N | K5: =IFERROR((D5/C5+F5/E5+H5/G5)/3,0)
A6: 46170 | B6: =TEXT(A6,"ddd") | C6: 3 | D6: =COUNTIFS(Orders!E:E,A6,Orders!F:F,"Cake") | E6: 4 | F6: =COUNTIFS(Orders!E:E,A6,Orders!F:F,"Cupcakes") | G6: 1 | H6: =COUNTIFS(Orders!E:E,A6,Orders!F:F,"Bomboloni") | I6: N | K6: =IFERROR((D6/C6+F6/E6+H6/G6)/3,0)
A7: 46171 | B7: =TEXT(A7,"ddd") | C7: 3 | D7: =COUNTIFS(Orders!E:E,A7,Orders!F:F,"Cake") | E7: 4 | F7: =COUNTIFS(Orders!E:E,A7,Orders!F:F,"Cupcakes") | G7: 1 | H7: =COUNTIFS(Orders!E:E,A7,Orders!F:F,"Bomboloni") | I7: N | K7: =IFERROR((D7/C7+F7/E7+H7/G7)/3,0)
A8: 46172 | B8: =TEXT(A8,"ddd") | C8: 5 | D8: =COUNTIFS(Orders!E:E,A8,Orders!F:F,"Cake") | E8: 4 | F8: =COUNTIFS(Orders!E:E,A8,Orders!F:F,"Cupcakes") | G8: 1 | H8: =COUNTIFS(Orders!E:E,A8,Orders!F:F,"Bomboloni") | I8: N | K8: =IFERROR((D8/C8+F8/E8+H8/G8)/3,0)
A9: 46173 | B9: =TEXT(A9,"ddd") | C9: 5 | D9: =COUNTIFS(Orders!E:E,A9,Orders!F:F,"Cake") | E9: 4 | F9: =COUNTIFS(Orders!E:E,A9,Orders!F:F,"Cupcakes") | G9: 1 | H9: =COUNTIFS(Orders!E:E,A9,Orders!F:F,"Bomboloni") | I9: N | K9: =IFERROR((D9/C9+F9/E9+H9/G9)/3,0)
A10: 46174 | B10: =TEXT(A10,"ddd") | C10: 3 | D10: =COUNTIFS(Orders!E:E,A10,Orders!F:F,"Cake") | E10: 4 | F10: =COUNTIFS(Orders!E:E,A10,Orders!F:F,"Cupcakes") | G10: 1 | H10: =COUNTIFS(Orders!E:E,A10,Orders!F:F,"Bomboloni") | I10: N | K10: =IFERROR((D10/C10+F10/E10+H10/G10)/3,0)
A11: 46175 | B11: =TEXT(A11,"ddd") | C11: 3 | D11: =COUNTIFS(Orders!E:E,A11,Orders!F:F,"Cake") | E11: 4 | F11: =COUNTIFS(Orders!E:E,A11,Orders!F:F,"Cupcakes") | G11: 1 | H11: =COUNTIFS(Orders!E:E,A11,Orders!F:F,"Bomboloni") | I11: N | K11: =IFERROR((D11/C11+F11/E11+H11/G11)/3,0)
A12: 46176 | B12: =TEXT(A12,"ddd") | C12: 3 | D12: =COUNTIFS(Orders!E:E,A12,Orders!F:F,"Cake") | E12: 4 | F12: =COUNTIFS(Orders!E:E,A12,Orders!F:F,"Cupcakes") | G12: 1 | H12: =COUNTIFS(Orders!E:E,A12,Orders!F:F,"Bomboloni") | I12: N | K12: =IFERROR((D12/C12+F12/E12+H12/G12)/3,0)
A13: 46177 | B13: =TEXT(A13,"ddd") | C13: 3 | D13: =COUNTIFS(Orders!E:E,A13,Orders!F:F,"Cake") | E13: 4 | F13: =COUNTIFS(Orders!E:E,A13,Orders!F:F,"Cupcakes") | G13: 1 | H13: =COUNTIFS(Orders!E:E,A13,Orders!F:F,"Bomboloni") | I13: N | K13: =IFERROR((D13/C13+F13/E13+H13/G13)/3,0)
... A61: 46225 | B61: =TEXT(A61,"ddd") | C61: 3 | D61: =COUNTIFS(Orders!E:E,A61,Orders!F:F,"Cake") | E61: 4 | F61: =COUNTIFS(Orders!E:E,A61,Orders!F:F,"Cupcakes") | G61: 1 | H61: =COUNTIFS(Orders!E:E,A61,Orders!F:F,"Bomboloni") | I61: N | K61: =IFERROR((D61/C61+F61/E61+H61/G61)/3,0)

Sheet Occasions Calendar
A1: Customer | B1: Occasion | C1: For whom | D1: Next date | E1: Notes | F1: First known year
A2: =QUERY({Occasions!C2:I,ARRAYFORMULA(IF(Occasions!E2:E="",,DATE(YEAR(TODAY())+IF(DATE(YEAR(TODAY()),VALUE(LEFT(Occasions!E2:E,2)),VALUE(RIGHT(Occasions!E2:E,2)))<TODAY(),1,0),VALUE(LEFT(Occasions!E2:E,2)),VALUE(RIGHT(Occasions!E2:E,2)))))},"select Col1, Col2, Col5, Col8, Col6, Col4 where Col8 is not null and Col8 <= date '"&TEXT(TODAY()+30,"yyyy-mm-dd")&"' and Col7 = 'Y' order by Col8 asc label Col1 'Customer', Col2 'Occasion', Col5 'For whom', Col8 'Next date', Col6 'Notes', Col4 'First known year'",0)
